rtl/SL.v
module SL_transiever (
  //Common signals
  input wire rst_n,
  input wire clk, //16MHz

  // SL related signals
  input wire serial_line_zeroes_a,
  input wire serial_line_ones_a,
  // output wire sl0,
  // output wire sl1,

 // APB related signals
 //Master APB signals
  input wire pclk_a,
  input wire preset_n_a,
  input wire [ 7:0] paddr_a, //let's pretend that this is HIGHER bits of address space, i mean sys_addr[31:24]. 
  //input wire [ 3:0] pstrb_a, //remove this also
  //input wire pprot_a[2:0], //dont need this also
  input wire psel_a, //Cant work only with address checking cause of bi-directional data bus
  input wire penable_a,
  input wire pwrite_a,
  //Slave APB signals
  //output wire pready_a, //lets think we dont need this signal cause we'll make fixed two cycles access
  //output wire pslverr_a, //all status info there is in `status` register which is freely accessed any time
  inout wire [31:0] pdata_a

    );

parameter STROB_POS = 8;
parameter CONFIG_ADDRESS  = 0'b0001;
parameter DATA_ADDRESS_WR = 0'b0010;
parameter DATA_ADDRESS_R  = 0'b0100;
parameter STATUS_ADDRESS  = 0'b1000;




//APB resynchronisation registers
reg [ 7:0] sync1_paddr_r;
reg [31:0] sync1_pdata_r;
reg [ 7:0] sync1_misc_r; //we DO NOT sync 'pclk' and 'preset_n'

reg [ 7:0] in_paddr_r;
reg [31:0] in_pdata_r;
reg [ 7:0] in_misc_r;

//wire {pprot, psel, penable, pwrite, pstrb[3:0]};

//assign {pprot, psel, penable, pwrite, pstrb[3:0]} = in_misc_r[7:0];


// SL receiver related registers
reg [15:0] sl0_tmp_r; //shift regs to temporary store input sequence
reg [15:0] sl1_tmp_r;
reg [31:0] shift_data_r;
reg [ 5:0] cycle_cnt_r;
reg [ 5:0] bit_cnt_r;
reg [ 4:0] state_r; //RECEIVER MODE: 0 - idle, 1 - receiveing started, 1a - bit detected, 1b - no bit, 1c - stop bit
                    //TRANSMITTER MODE: 0 - idle, 1 - sending a word

reg [31:0] buffered_data_r;
reg [31:0] data_to_send_r;
reg [15:0] config_r; //[0] - parity check, [6:1] - bit cnt(8-32bits), [7] - rxtx mode, [8] - IRQ mode ####address on config_r is 0 (zero)
reg [15:0] status_r; //[0] - word length fail, [1] - word receiveing process going, [2] - empty
                    //[3] - word received, [4] - parity error, [5] - level error on line,
reg parity_ones;
reg parity_zeroes;

//Synchronisation registers to read from corresponding registers via APB
reg [31:0] sync1_buffered_data_r;
reg [15:0] sync1_config_r;
reg [15:0] sync1_status_r;

reg [31:0] apb_buffered_data_r;
reg [15:0] apb_config_r;
reg [15:0] apb_status_r;
reg [31:0] apb_muxed_out_r;

//Synchronisation registers to write to corresponding registers via APB
reg [31:0] sync1_data_to_send_r;
reg [15:0] sync3_config_r;

reg [31:0] sync2_data_to_send_r;
reg [15:0] sync2_config_r;



reg [2:0] apb_state; //001 - IDLE, 010 - SETUP, 100 - ACCESS




assign pdata_a = ( penable_a && psel_a && !pwrite_a ) ? apb_muxed_out_r : 32'bz;






always @(posedge clk or negedge rst_n or negedge preset_n_a) begin 
if( !rst_n | !preset_n_a ) begin
  sl0_tmp_r[15:0]       <= 16'hAAAA;
  sl1_tmp_r[15:0]       <= 16'hAAAA;
  shift_data_r[31:0]    <= 0;
  cycle_cnt_r[5:0]      <= 0;
  bit_cnt_r[5:0]        <= 0;
  state_r[4:0]          <= 5'b00001;
  buffered_data_r[31:0] <= 0;
  data_to_send_r[31:0]  <= 0;
  config_r[15:0]        <= 16'h0020;
  status_r[15:0]        <= 0;   
  parity_zeroes         <= 0;
  parity_ones           <= 1;   
end else  if( !config_r[7] )  //RECEIVER ROUTINE
  begin
    sl0_tmp_r[15:0] <= ( sl0_tmp_r << 1 ) | serial_line_zeroes_a ;
    sl1_tmp_r[15:0] <= ( sl1_tmp_r << 1 ) | serial_line_ones_a;
    case (state_r)
      5'b00001: begin //IDLE state, waiting for active transmission sequence on one of input lines
                  if( (sl0_tmp_r[15:12] == 4'hF && sl0_tmp_r[3:0] == 4'h0) || (sl1_tmp_r[15:12] == 4'hF && sl1_tmp_r[3:0] == 4'h0) )
                  begin
                    state_r <= state_r << 1;
                    cycle_cnt_r <= 3;
                    status_r[0] <= 0; //word length ok
                    status_r[1] <= 1; //receiving process on
                    status_r[3] <= 0; //Word received flag off
                    status_r[4] <= 0; //no parity error atm
                    status_r[5] <= 0; //no level errors on line
                  end
                  else begin
                    status_r[0] <= 0; //word length ok
                    status_r[1] <= 0; //receiving process off
                    status_r[3] <= 0; //Word received flag off
                    status_r[4] <= 0; //no parity error atm
                    status_r[5] <= 0; //no level errors on line
                  end
                end
      5'b00010: begin //RECEIVING state
                  if( cycle_cnt_r == STROB_POS )
                  begin
                    state_r <= state_r << 1;
                    if ( !serial_line_ones_a && !serial_line_zeroes_a ) //Если стоп-бит
                    begin
                      parity_zeroes <= 0;
                      parity_ones   <= 1;
                      shift_data_r  <= 0;
                      bit_cnt_r     <= 0;
                      if( bit_cnt_r[5:0] == config_r[6:1] + 1 ) //Проверяем количество принятых разрядов
                      begin
                        status_r[0] <= 0; //word length ok
                        status_r[1] <= 0; //receiving process ended
                        status_r[2] <= 0; //as word correctly received, no noise on inout lines
                        status_r[3] <= 1; //word received

                        if( (parity_zeroes || !parity_ones ) && config_r[0] )  buffered_data_r <= 0;
                        else  buffered_data_r <= shift_data_r;
                      end
                      else begin
                        status_r[0] <= 1; //word length fail
                        status_r[1] <= 0; //receiving process ended
                        status_r[2] <= 0; //as word correctly received, no noise on inout lines
                        status_r[3] <= 0; //word is not received
                      end

                      if( !parity_zeroes && !parity_ones ) status_r[4] <= 0; //parity ok
                      else status_r[4] <= 1; //parity check fail
                    end
                    else 
                    begin
                      bit_cnt_r <= bit_cnt_r + 1;
                      if ( !serial_line_ones_a ) //Если единичка
                        begin
                          shift_data_r <= ( shift_data_r >> 1 ) | 32'h8000_0000; //Store data in high bits of register
                          parity_ones  <= parity_ones ^ 1;
                        end
                        else  //Если нолик
                          begin
                            shift_data_r  <= ( shift_data_r >> 1 ) & 32'h7FFF_FFFF;
                            parity_zeroes <= parity_zeroes ^ 1;
                          end
                    end
                  end
                  else cycle_cnt_r <= cycle_cnt_r + 1;
                end    
      5'b00100: begin //WAITING for bit transmission end state
                  if( sl0_tmp_r[7:0] == 8'hFF && sl1_tmp_r[7:0] == 8'hFF )
                  begin
                    state_r <= state_r >> 2; //go to the IDLE state
                    cycle_cnt_r <= 0;
                  end
                  else cycle_cnt_r <= cycle_cnt_r + 1;
                end
      default: state_r <= 5'b00001;
    endcase
  end
  else begin //TRANSMITTER routine
    state_r <= 5'b00001;
  end

end

always @(posedge pclk_a or negedge rst_n or negedge preset_n_a) begin
  if ( !rst_n || !preset_n_a ) begin
    // sync1_buffered_data_r <= 32'h0000_0000;
    // sync1_config_r        <= 16'h0000;
    // sync1_status_r        <= 16'h0000;

    // apb_buffered_data_r   <= 32'h0000_0000;
    // apb_config_r          <= 16'h0000;
    // apb_status_r          <= 16'h0000;
    
        
    sync1_buffered_data_r <= 32'h0000_0000;
    sync1_config_r        <= config_r;
    sync1_status_r        <= status_r;

    //Second stage sync
    apb_buffered_data_r   <= sync1_buffered_data_r;
    apb_config_r          <= sync1_config_r;
    apb_status_r          <= sync1_status_r;

  end
  else begin
    //First stage sync, have to do this cause we need to read data in two cycles, so data must be ready every time and all routines must work related to APB clk
    sync1_buffered_data_r <= buffered_data_r;
    sync1_config_r        <= config_r;
    sync1_status_r        <= status_r;

    //Second stage sync
    apb_buffered_data_r   <= sync1_buffered_data_r;
    apb_config_r          <= sync1_config_r;
    apb_status_r          <= sync1_status_r;

    // case( apb_state )
    // 3'b001: begin //IDLE state, PSELx = 0, PENABLE = 0
              if( psel_a && !penable_a ) begin
                // apb_state <= 3'b010;

                if( pwrite_a ) begin // WRITE sequence
                  case( paddr_a )
                    CONFIG_ADDRESS: begin
                                      config_r[15:0] <= in_pdata_r[15:0];
                                    end
                    DATA_ADDRESS_WR:  begin
                                        data_to_send_r[31:0] <= in_pdata_r[31:0];
                                      end
                    default:  begin
                              end
                  endcase            
                end
                else begin //READ sequence
                  case( paddr_a )
                    CONFIG_ADDRESS: begin
                                      apb_muxed_out_r[31:0] <= { 16'b0000_0000_0000_0000, apb_config_r[15:0] };
                                    end
                    DATA_ADDRESS_R: begin
                                      apb_muxed_out_r[31:0] <= apb_buffered_data_r[31:0];
                                    end
                    STATUS_ADDRESS: begin
                                      apb_muxed_out_r[31:0] <= { 16'b0000_0000_0000_0000, apb_status_r[15:0] };
                                    end
                    default:  begin
                                apb_muxed_out_r[31:0] <= 32'h0000_0000;
                              end
                  endcase
                end
              end

    //           end else apb_state <= 3'b001;
    //         end
    // 3'b010: begin //SETUP state, PSELx = 1, PENABLE = 0
    //           apb_state <= 3'b001;

    //         end
    // 3'b100: begin //ACCESS state, PSELx = 1, PENABLE = 1
    //           apb_state <= 3'b001;
    //         end
    // default: apb_state <= 3'b001;

    // endcase

  end
end


endmodule

bench/hdl/tb_SL.v
`timescale 1ns / 100ps

module sl_rt_tb;

reg reset;       // Common asycnhronous reset
reg clk;
parameter tck = 10; // clock tick
reg sl0;
reg sl1;
reg pclk;
reg preset_n;
reg [ 7:0] paddr;
reg psel; //Cant work only with address checking cause of bi-directional data bus
reg penable;
reg pwrite;
wire [31:0] pdata;


SL_transiever dut(reset, clk, sl0, sl1, clk, reset, paddr, psel, penable, pwrite, pdata);

//Error injection parameters
reg ei_data_sl0;
reg ei_data_sl1;
reg ei_quantity;
reg ei_parity;
reg ei_fh;  //freq high
reg ei_fl;  //freq low
reg ei_noise_sl0;
reg ei_noise_sl1;


parameter pause_between_words = 0;
parameter value_of_pause = 160; //in clock cycles
parameter word_legth_min = 8;
parameter word_length_max = 32;
parameter word_length_incr = 1;

reg parity0;
reg parity1;

reg fl_ei_data_sl0; //
reg fl_ei_data_sl1;//
reg fl_ei_quantity;
reg fl_ei_fh;  //freq high
reg fl_ei_fl;  //freq low
reg fl_ei_noise_sl0;//
reg fl_ei_noise_sl1;//



//Other parameters
parameter reset_after_each_word = 0;
parameter start_word = 0;
parameter finish_word = 32'hFFFF_FFFF;
parameter increment_word = 8'h1E;


int var1 = 0;
int i = 0;
int word = 0;
int ini_word = 0;

always #(tck/2) clk <= ~clk; // clocking device
always #(tck/2) pclk <= ~pclk; // clocking device

initial begin
  $dumpfile("sl_rt.vcd");
  $dumpvars(0, dut);
  $monitor($stime,, reset,, clk,,, sl0, sl1); 
end

// testbench actions
initial 
begin
  pclk     = 0;
  preset_n = 0;
  paddr    = 0;
  psel     = 0;
  penable  = 0;
  pwrite   = 0;


  clk   = 0; 
  reset = 0;
  sl0   = 0;
  sl1   = 0;
  #(tck*10);
  reset = 1;
  preset_n = 1;
  #(tck*2);



  ini_word = $urandom_range(0,16'hFFFF);
  word = ini_word;
  ei_data_sl0   = 0;
  ei_data_sl1   = 0;
  ei_quantity   = 0;
  ei_parity     = 0;
  ei_fh         = 0;  //freq high
  ei_fl         = 0;  //freq low
  ei_noise_sl0  = 0;
  ei_noise_sl1  = 0;

  fl_ei_data_sl0 = 0; //
  fl_ei_data_sl1 = 0;//
  fl_ei_quantity = 0;
  fl_ei_fh = 0;  //freq high
  fl_ei_fl = 0;  //freq low
  fl_ei_noise_sl0 = 0;//
  fl_ei_noise_sl1 = 0;//
  sl0 = 1;
  sl1 = 1;
  parity0  = 0;
  parity1  = 0;
  #(tck*16);

      i = 16;
    //for( i = word_legth_min; i <= word_length_max; i = i + word_length_incr ) begin
      for( var1 = 0; var1 < i; var1 = var1 + 1) begin
        if( word & 1 ) begin

          sl1 = 0;
          parity1 = parity1 ^ 1;
          #(tck*16);
          sl1 = 1;
          #(tck*8);

          if( !fl_ei_data_sl1 && ei_data_sl1 ) begin
            sl1 = 0;
            #(tck*4);
            sl1 = 1;
            #(tck*4);
            fl_ei_data_sl0 = 1;
          end else if( !fl_ei_noise_sl1 && ei_noise_sl1 ) begin
            sl1 = 0;
            #(tck*1);
            sl1 = 1;
            #(tck*7);
            fl_ei_noise_sl1 = 1;
          end
          else #(tck*8);

        end
        else begin
          sl0 = 0;
          parity0 = parity0 ^ 1;
          #(tck*16);
          sl0 = 1;
          #(tck*4);

          if( !fl_ei_data_sl0 && ei_data_sl0 ) begin
            sl0 = 0;
            #(tck*4);
            sl0 = 1;
            #(tck*4);
            fl_ei_data_sl0 = 1;
          end
          else if( !fl_ei_noise_sl0 && ei_noise_sl0 ) begin
            sl0 = 0;
            #(tck*1);
            sl0 = 1;
            #(tck*7);
            fl_ei_noise_sl0 = 1;
          end
          else #(tck*8);

        end
        word = word >> 1;
      end

      // add parity bit
      if( parity1 && ei_parity ) begin
        sl0 = 0;
        #(tck*16);
        sl0 = 1;
        #(tck*16);
      end
      else begin
        sl1 = 0;
        #(tck*16);
        sl1 = 1;
        #(tck*16);
      end

      // add stop bit
      sl1 = 0;
      sl0 = 0;
      #(tck*16);
      sl0 = 1;
      sl1 = 1;
      #(tck*16);

      //add delay after word
      #(tck*16);

      #(tck/2);
      //APB master read sequence
      paddr  <= 4'b0100;
      pwrite <= 0;
      psel   <= 1;
      #tck;

      penable <= 1;
      #tck;

      paddr   <= 0;
      pwrite  <= 0;
      psel    <= 0;
      penable <= 0;

      #tck;
      paddr  <= 4'b1000;
      pwrite <= 0;
      psel   <= 1;
      #tck;

      penable <= 1;
      #tck;

      paddr   <= 0;
      pwrite  <= 0;
      psel    <= 0;
      penable <= 0;


end
endmodule

sim/sl_rt.vcd
$date
	Thu Oct 12 16:33:21 2017
$end
$version
	ModelSim Version 10.5
$end
$timescale
	100ps
$end

$scope module sl_rt_tb $end

$scope module dut $end
$var parameter 32 ! STROB_POS $end
$var parameter 32 " CONFIG_ADDRESS $end
$var parameter 32 # DATA_ADDRESS_WR $end
$var parameter 32 $ DATA_ADDRESS_R $end
$var parameter 32 % STATUS_ADDRESS $end
$var wire 1 & rst_n $end
$var wire 1 ' clk $end
$var wire 1 ( serial_line_zeroes_a $end
$var wire 1 ) serial_line_ones_a $end
$var wire 1 * pclk_a $end
$var wire 1 + preset_n_a $end
$var wire 1 , paddr_a [7] $end
$var wire 1 - paddr_a [6] $end
$var wire 1 . paddr_a [5] $end
$var wire 1 / paddr_a [4] $end
$var wire 1 0 paddr_a [3] $end
$var wire 1 1 paddr_a [2] $end
$var wire 1 2 paddr_a [1] $end
$var wire 1 3 paddr_a [0] $end
$var wire 1 4 psel_a $end
$var wire 1 5 penable_a $end
$var wire 1 6 pwrite_a $end
$var wire 1 7 pdata_a [31] $end
$var wire 1 8 pdata_a [30] $end
$var wire 1 9 pdata_a [29] $end
$var wire 1 : pdata_a [28] $end
$var wire 1 ; pdata_a [27] $end
$var wire 1 < pdata_a [26] $end
$var wire 1 = pdata_a [25] $end
$var wire 1 > pdata_a [24] $end
$var wire 1 ? pdata_a [23] $end
$var wire 1 @ pdata_a [22] $end
$var wire 1 A pdata_a [21] $end
$var wire 1 B pdata_a [20] $end
$var wire 1 C pdata_a [19] $end
$var wire 1 D pdata_a [18] $end
$var wire 1 E pdata_a [17] $end
$var wire 1 F pdata_a [16] $end
$var wire 1 G pdata_a [15] $end
$var wire 1 H pdata_a [14] $end
$var wire 1 I pdata_a [13] $end
$var wire 1 J pdata_a [12] $end
$var wire 1 K pdata_a [11] $end
$var wire 1 L pdata_a [10] $end
$var wire 1 M pdata_a [9] $end
$var wire 1 N pdata_a [8] $end
$var wire 1 O pdata_a [7] $end
$var wire 1 P pdata_a [6] $end
$var wire 1 Q pdata_a [5] $end
$var wire 1 R pdata_a [4] $end
$var wire 1 S pdata_a [3] $end
$var wire 1 T pdata_a [2] $end
$var wire 1 U pdata_a [1] $end
$var wire 1 V pdata_a [0] $end
$var reg 8 W sync1_paddr_r [7:0] $end
$var reg 32 X sync1_pdata_r [31:0] $end
$var reg 8 Y sync1_misc_r [7:0] $end
$var reg 8 Z in_paddr_r [7:0] $end
$var reg 32 [ in_pdata_r [31:0] $end
$var reg 8 \ in_misc_r [7:0] $end
$var reg 16 ] sl0_tmp_r [15:0] $end
$var reg 16 ^ sl1_tmp_r [15:0] $end
$var reg 32 _ shift_data_r [31:0] $end
$var reg 6 ` cycle_cnt_r [5:0] $end
$var reg 6 a bit_cnt_r [5:0] $end
$var reg 5 b state_r [4:0] $end
$var reg 32 c buffered_data_r [31:0] $end
$var reg 32 d data_to_send_r [31:0] $end
$var reg 16 e config_r [15:0] $end
$var reg 16 f status_r [15:0] $end
$var reg 1 g parity_ones $end
$var reg 1 h parity_zeroes $end
$var reg 32 i sync1_buffered_data_r [31:0] $end
$var reg 16 j sync1_config_r [15:0] $end
$var reg 16 k sync1_status_r [15:0] $end
$var reg 32 l apb_buffered_data_r [31:0] $end
$var reg 16 m apb_config_r [15:0] $end
$var reg 16 n apb_status_r [15:0] $end
$var reg 32 o apb_muxed_out_r [31:0] $end
$var reg 32 p sync1_data_to_send_r [31:0] $end
$var reg 16 q sync3_config_r [15:0] $end
$var reg 32 r sync2_data_to_send_r [31:0] $end
$var reg 16 s sync2_config_r [15:0] $end
$var reg 3 t apb_state [2:0] $end
$upscope $end
$upscope $end
$enddefinitions $end
#0
$dumpvars
bx W
bx X
bx Y
bx Z
bx [
bx \
b1010101010101010 ]
b1010101010101010 ^
b0 _
b0 `
b0 a
b1 b
b0 c
b0 d
b100000 e
b0 f
1g
0h
b0 i
bx j
bx k
bx l
bx m
bx n
bx o
bx p
bx q
bx r
bx s
bx t
b1000 !
b1 "
b10 #
b100 $
b1000 %
zV
zU
zT
zS
zR
zQ
zP
zO
zN
zM
zL
zK
zJ
zI
zH
zG
zF
zE
zD
zC
zB
zA
z@
z?
z>
z=
z<
z;
z:
z9
z8
z7
0&
0'
0(
0)
0*
0+
03
02
01
00
0/
0.
0-
0,
04
05
06
$end
#50
1*
1'
b100000 j
b0 k
b0 l
#100
0*
0'
#150
1*
1'
b100000 m
b0 n
#200
0*
0'
#250
1*
1'
#300
0*
0'
#350
1*
1'
#400
0*
0'
#450
1*
1'
#500
0*
0'
#550
1*
1'
#600
0*
0'
#650
1*
1'
#700
0*
0'
#750
1*
1'
#800
0*
0'
#850
1*
1'
#900
0*
0'
#950
1*
1'
#1000
1+
1&
0*
0'
#1050
1*
1'
b101010101010100 ]
b101010101010100 ^
#1100
0*
0'
#1150
1*
1'
b1010101010101000 ]
b1010101010101000 ^
#1200
1(
1)
0*
0'
#1250
1*
1'
b101010101010001 ]
b101010101010001 ^
#1300
0*
0'
#1350
1*
1'
b1010101010100011 ]
b1010101010100011 ^
#1400
0*
0'
#1450
1*
1'
b101010101000111 ]
b101010101000111 ^
#1500
0*
0'
#1550
1*
1'
b1010101010001111 ]
b1010101010001111 ^
#1600
0*
0'
#1650
1*
1'
b101010100011111 ]
b101010100011111 ^
#1700
0*
0'
#1750
1*
1'
b1010101000111111 ]
b1010101000111111 ^
#1800
0*
0'
#1850
1*
1'
b101010001111111 ]
b101010001111111 ^
#1900
0*
0'
#1950
1*
1'
b1010100011111111 ]
b1010100011111111 ^
#2000
0*
0'
#2050
1*
1'
b101000111111111 ]
b101000111111111 ^
#2100
0*
0'
#2150
1*
1'
b1010001111111111 ]
b1010001111111111 ^
#2200
0*
0'
#2250
1*
1'
b100011111111111 ]
b100011111111111 ^
#2300
0*
0'
#2350
1*
1'
b1000111111111111 ]
b1000111111111111 ^
#2400
0*
0'
#2450
1*
1'
b1111111111111 ]
b1111111111111 ^
#2500
0*
0'
#2550
1*
1'
b11111111111111 ]
b11111111111111 ^
#2600
0*
0'
#2650
1*
1'
b111111111111111 ]
b111111111111111 ^
#2700
0*
0'
#2750
1*
1'
b1111111111111111 ]
b1111111111111111 ^
#2800
0(
0*
0'
#2850
1*
1'
b1111111111111110 ]
#2900
0*
0'
#2950
1*
1'
b1111111111111100 ]
#3000
0*
0'
#3050
1*
1'
b1111111111111000 ]
#3100
0*
0'
#3150
1*
1'
b1111111111110000 ]
#3200
0*
0'
#3250
1*
1'
b1111111111100000 ]
b10 b
b11 `
b10 f
#3300
0*
0'
#3350
1*
1'
b1111111111000000 ]
b100 `
b10 k
#3400
0*
0'
#3450
1*
1'
b1111111110000000 ]
b101 `
b10 n
#3500
0*
0'
#3550
1*
1'
b1111111100000000 ]
b110 `
#3600
0*
0'
#3650
1*
1'
b1111111000000000 ]
b111 `
#3700
0*
0'
#3750
1*
1'
b1111110000000000 ]
b1000 `
#3800
0*
0'
#3850
1*
1'
b1111100000000000 ]
b100 b
b1 a
1h
#3900
0*
0'
#3950
1*
1'
b1111000000000000 ]
b1001 `
#4000
0*
0'
#4050
1*
1'
b1110000000000000 ]
b1010 `
#4100
0*
0'
#4150
1*
1'
b1100000000000000 ]
b1011 `
#4200
0*
0'
#4250
1*
1'
b1000000000000000 ]
b1100 `
#4300
0*
0'
#4350
1*
1'
b0 ]
b1101 `
#4400
1(
0*
0'
#4450
1*
1'
b1 ]
b1110 `
#4500
0*
0'
#4550
1*
1'
b11 ]
b1111 `
#4600
0*
0'
#4650
1*
1'
b111 ]
b10000 `
#4700
0*
0'
#4750
1*
1'
b1111 ]
b10001 `
#4800
0*
0'
#4850
1*
1'
b11111 ]
b10010 `
#4900
0*
0'
#4950
1*
1'
b111111 ]
b10011 `
#5000
0*
0'
#5050
1*
1'
b1111111 ]
b10100 `
#5100
0*
0'
#5150
1*
1'
b11111111 ]
b10101 `
#5200
0*
0'
#5250
1*
1'
b111111111 ]
b1 b
b0 `
#5300
0*
0'
#5350
1*
1'
b1111111111 ]
b0 f
#5400
0*
0'
#5450
1*
1'
b11111111111 ]
b0 k
#5500
0*
0'
#5550
1*
1'
b111111111111 ]
b0 n
#5600
0)
0*
0'
#5650
1*
1'
b1111111111111 ]
b1111111111111110 ^
#5700
0*
0'
#5750
1*
1'
b11111111111111 ]
b1111111111111100 ^
#5800
0*
0'
#5850
1*
1'
b111111111111111 ]
b1111111111111000 ^
#5900
0*
0'
#5950
1*
1'
b1111111111111111 ]
b1111111111110000 ^
#6000
0*
0'
#6050
1*
1'
b1111111111100000 ^
b10 b
b11 `
b10 f
#6100
0*
0'
#6150
1*
1'
b1111111111000000 ^
b100 `
b10 k
#6200
0*
0'
#6250
1*
1'
b1111111110000000 ^
b101 `
b10 n
#6300
0*
0'
#6350
1*
1'
b1111111100000000 ^
b110 `
#6400
0*
0'
#6450
1*
1'
b1111111000000000 ^
b111 `
#6500
0*
0'
#6550
1*
1'
b1111110000000000 ^
b1000 `
#6600
0*
0'
#6650
1*
1'
b1111100000000000 ^
b100 b
b10 a
b10000000000000000000000000000000 _
0g
#6700
0*
0'
#6750
1*
1'
b1111000000000000 ^
b1001 `
#6800
0*
0'
#6850
1*
1'
b1110000000000000 ^
b1010 `
#6900
0*
0'
#6950
1*
1'
b1100000000000000 ^
b1011 `
#7000
0*
0'
#7050
1*
1'
b1000000000000000 ^
b1100 `
#7100
0*
0'
#7150
1*
1'
b0 ^
b1101 `
#7200
1)
0*
0'
#7250
1*
1'
b1 ^
b1110 `
#7300
0*
0'
#7350
1*
1'
b11 ^
b1111 `
#7400
0*
0'
#7450
1*
1'
b111 ^
b10000 `
#7500
0*
0'
#7550
1*
1'
b1111 ^
b10001 `
#7600
0*
0'
#7650
1*
1'
b11111 ^
b10010 `
#7700
0*
0'
#7750
1*
1'
b111111 ^
b10011 `
#7800
0*
0'
#7850
1*
1'
b1111111 ^
b10100 `
#7900
0*
0'
#7950
1*
1'
b11111111 ^
b10101 `
#8000
0*
0'
#8050
1*
1'
b111111111 ^
b1 b
b0 `
#8100
0*
0'
#8150
1*
1'
b1111111111 ^
b0 f
#8200
0*
0'
#8250
1*
1'
b11111111111 ^
b0 k
#8300
0*
0'
#8350
1*
1'
b111111111111 ^
b0 n
#8400
0*
0'
#8450
1*
1'
b1111111111111 ^
#8500
0*
0'
#8550
1*
1'
b11111111111111 ^
#8600
0*
0'
#8650
1*
1'
b111111111111111 ^
#8700
0*
0'
#8750
1*
1'
b1111111111111111 ^
#8800
0)
0*
0'
#8850
1*
1'
b1111111111111110 ^
#8900
0*
0'
#8950
1*
1'
b1111111111111100 ^
#9000
0*
0'
#9050
1*
1'
b1111111111111000 ^
#9100
0*
0'
#9150
1*
1'
b1111111111110000 ^
#9200
0*
0'
#9250
1*
1'
b1111111111100000 ^
b10 b
b11 `
b10 f
#9300
0*
0'
#9350
1*
1'
b1111111111000000 ^
b100 `
b10 k
#9400
0*
0'
#9450
1*
1'
b1111111110000000 ^
b101 `
b10 n
#9500
0*
0'
#9550
1*
1'
b1111111100000000 ^
b110 `
#9600
0*
0'
#9650
1*
1'
b1111111000000000 ^
b111 `
#9700
0*
0'
#9750
1*
1'
b1111110000000000 ^
b1000 `
#9800
0*
0'
#9850
1*
1'
b1111100000000000 ^
b100 b
b11 a
b11000000000000000000000000000000 _
1g
#9900
0*
0'
#9950
1*
1'
b1111000000000000 ^
b1001 `
#10000
0*
0'
#10050
1*
1'
b1110000000000000 ^
b1010 `
#10100
0*
0'
#10150
1*
1'
b1100000000000000 ^
b1011 `
#10200
0*
0'
#10250
1*
1'
b1000000000000000 ^
b1100 `
#10300
0*
0'
#10350
1*
1'
b0 ^
b1101 `
#10400
1)
0*
0'
#10450
1*
1'
b1 ^
b1110 `
#10500
0*
0'
#10550
1*
1'
b11 ^
b1111 `
#10600
0*
0'
#10650
1*
1'
b111 ^
b10000 `
#10700
0*
0'
#10750
1*
1'
b1111 ^
b10001 `
#10800
0*
0'
#10850
1*
1'
b11111 ^
b10010 `
#10900
0*
0'
#10950
1*
1'
b111111 ^
b10011 `
#11000
0*
0'
#11050
1*
1'
b1111111 ^
b10100 `
#11100
0*
0'
#11150
1*
1'
b11111111 ^
b10101 `
#11200
0*
0'
#11250
1*
1'
b111111111 ^
b1 b
b0 `
#11300
0*
0'
#11350
1*
1'
b1111111111 ^
b0 f
#11400
0*
0'
#11450
1*
1'
b11111111111 ^
b0 k
#11500
0*
0'
#11550
1*
1'
b111111111111 ^
b0 n
#11600
0*
0'
#11650
1*
1'
b1111111111111 ^
#11700
0*
0'
#11750
1*
1'
b11111111111111 ^
#11800
0*
0'
#11850
1*
1'
b111111111111111 ^
#11900
0*
0'
#11950
1*
1'
b1111111111111111 ^
#12000
0(
0*
0'
#12050
1*
1'
b1111111111111110 ]
#12100
0*
0'
#12150
1*
1'
b1111111111111100 ]
#12200
0*
0'
#12250
1*
1'
b1111111111111000 ]
#12300
0*
0'
#12350
1*
1'
b1111111111110000 ]
#12400
0*
0'
#12450
1*
1'
b1111111111100000 ]
b10 b
b11 `
b10 f
#12500
0*
0'
#12550
1*
1'
b1111111111000000 ]
b100 `
b10 k
#12600
0*
0'
#12650
1*
1'
b1111111110000000 ]
b101 `
b10 n
#12700
0*
0'
#12750
1*
1'
b1111111100000000 ]
b110 `
#12800
0*
0'
#12850
1*
1'
b1111111000000000 ]
b111 `
#12900
0*
0'
#12950
1*
1'
b1111110000000000 ]
b1000 `
#13000
0*
0'
#13050
1*
1'
b1111100000000000 ]
b100 b
b100 a
b1100000000000000000000000000000 _
0h
#13100
0*
0'
#13150
1*
1'
b1111000000000000 ]
b1001 `
#13200
0*
0'
#13250
1*
1'
b1110000000000000 ]
b1010 `
#13300
0*
0'
#13350
1*
1'
b1100000000000000 ]
b1011 `
#13400
0*
0'
#13450
1*
1'
b1000000000000000 ]
b1100 `
#13500
0*
0'
#13550
1*
1'
b0 ]
b1101 `
#13600
1(
0*
0'
#13650
1*
1'
b1 ]
b1110 `
#13700
0*
0'
#13750
1*
1'
b11 ]
b1111 `
#13800
0*
0'
#13850
1*
1'
b111 ]
b10000 `
#13900
0*
0'
#13950
1*
1'
b1111 ]
b10001 `
#14000
0*
0'
#14050
1*
1'
b11111 ]
b10010 `
#14100
0*
0'
#14150
1*
1'
b111111 ]
b10011 `
#14200
0*
0'
#14250
1*
1'
b1111111 ]
b10100 `
#14300
0*
0'
#14350
1*
1'
b11111111 ]
b10101 `
#14400
0*
0'
#14450
1*
1'
b111111111 ]
b1 b
b0 `
#14500
0*
0'
#14550
1*
1'
b1111111111 ]
b0 f
#14600
0*
0'
#14650
1*
1'
b11111111111 ]
b0 k
#14700
0*
0'
#14750
1*
1'
b111111111111 ]
b0 n
#14800
0(
0*
0'
#14850
1*
1'
b1111111111110 ]
#14900
0*
0'
#14950
1*
1'
b11111111111100 ]
#15000
0*
0'
#15050
1*
1'
b111111111111000 ]
#15100
0*
0'
#15150
1*
1'
b1111111111110000 ]
#15200
0*
0'
#15250
1*
1'
b1111111111100000 ]
b10 b
b11 `
b10 f
#15300
0*
0'
#15350
1*
1'
b1111111111000000 ]
b100 `
b10 k
#15400
0*
0'
#15450
1*
1'
b1111111110000000 ]
b101 `
b10 n
#15500
0*
0'
#15550
1*
1'
b1111111100000000 ]
b110 `
#15600
0*
0'
#15650
1*
1'
b1111111000000000 ]
b111 `
#15700
0*
0'
#15750
1*
1'
b1111110000000000 ]
b1000 `
#15800
0*
0'
#15850
1*
1'
b1111100000000000 ]
b100 b
b101 a
b110000000000000000000000000000 _
1h
#15900
0*
0'
#15950
1*
1'
b1111000000000000 ]
b1001 `
#16000
0*
0'
#16050
1*
1'
b1110000000000000 ]
b1010 `
#16100
0*
0'
#16150
1*
1'
b1100000000000000 ]
b1011 `
#16200
0*
0'
#16250
1*
1'
b1000000000000000 ]
b1100 `
#16300
0*
0'
#16350
1*
1'
b0 ]
b1101 `
#16400
1(
0*
0'
#16450
1*
1'
b1 ]
b1110 `
#16500
0*
0'
#16550
1*
1'
b11 ]
b1111 `
#16600
0*
0'
#16650
1*
1'
b111 ]
b10000 `
#16700
0*
0'
#16750
1*
1'
b1111 ]
b10001 `
#16800
0*
0'
#16850
1*
1'
b11111 ]
b10010 `
#16900
0*
0'
#16950
1*
1'
b111111 ]
b10011 `
#17000
0*
0'
