rtl/SL.v
module SL_transiever (
  //Common siglans
  input wire rst_n,
  input wire clk, //16MHz

  // SL related signals
  input wire serial_line_zeroes_a,
  input wire serial_line_ones_a
  // output wire sl0,
  // output wire sl1,

  //APB related signals
  // input wire pclk,
  // input wire preset_n,
  // input wire [7:0] paddr,
  // input wire pprot,
  // input wire psel,
  // input wire penable,
  // input wire pwrite,
  // inout wire [31:0]pdata,
  // input wire pstrb,
  // output wire pready,
  // output wire pslverr

    );

parameter STROB_POS = 8;

reg [15:0] sl0_tmp_r; //shift regs to temporary store input sequence
reg [15:0] sl1_tmp_r;
reg [31:0] shift_data_r;
reg [ 5:0]  cycle_cnt_r;
reg [ 5:0]  bit_cnt_r;
reg [ 4:0]  state_r; //RECEIVER MODE: 0 - idle, 1 - receiveing started, 1a - bit detected, 1b - no bit, 1c - stop bit
                    //TRANSMITTER MODE: 0 - idle, 1 - sending a word

reg [31:0] buffered_data_r;
reg [63:0] data_to_send_r;
reg [15:0] config_r; //[0] - parity check, [6:1] - bit cnt(8-32bits), [7] - rxtx mode, [8] - IRQ mode
reg [15:0] status_r; //[0] - word length fail, [1] - word receiveing process going, [2] - noise on input lines
                    //[3] - word received, [4] - parity error, [5] - level error on line,
reg parity_ones;
reg parity_zeroes;

always @(posedge clk)
begin
  if( rst_n == 1'b0 ) begin //| preset_n == 1'b0 )
    sl0_tmp_r[15:0]       <= 16'hAAAA;
    sl1_tmp_r[15:0]       <= 16'hAAAA;
    shift_data_r[31:0]    <= 0;
    cycle_cnt_r[5:0]      <= 0;
    bit_cnt_r[5:0]        <= 0;
    state_r[4:0]          <= 5'b00001;
    buffered_data_r[31:0] <= 0;
    data_to_send_r[63:0]  <= 0;
    config_r[15:0]        <= 16'b0000_0000_0010_0000;
    status_r[15:0]        <= 0;   
    parity_zeroes         <= 0;
    parity_ones           <= 1;   

  end
end


always @(posedge clk) begin 
  if( !config_r[7] )  //RECEIVER ROUTINE
  begin
    sl0_tmp_r[15:0] <= ( sl0_tmp_r << 1 ) | serial_line_zeroes_a ;
    sl1_tmp_r[15:0] <= ( sl1_tmp_r << 1 ) | serial_line_ones_a;
    case (state_r)
      5'b00001: begin //IDLE state, waiting for active transmission sequence on one of input lines
                  if( (sl0_tmp_r[15:12] == 4'b1111 && sl0_tmp_r[3:0] == 4'b0000) || (sl1_tmp_r[15:12] == 4'b1111 && sl1_tmp_r[3:0] == 4'b0000) )
                  begin
                    state_r <= state_r << 1;
                    cycle_cnt_r <= 3;
                    status_r[0] <= 0; //word length ok
                    status_r[1] <= 1; //receiving process on
                    status_r[2] <= 0; //as word correctly received, no noise on inout lines
                    status_r[3] <= 0; //Word received flag off
                    status_r[4] <= 0; //no parity error atm
                    status_r[5] <= 0; //no level errors on line
                  end
                  else if( sl0_tmp_r[2:0] == 3'b101 || sl1_tmp_r[2:0] == 3'b101 )  status_r[2] <= 1; //Noise on line
                    else status_r[2] <= 0;
                end
      5'b00010: begin //RECEIVING state
                  cycle_cnt_r <= cycle_cnt_r + 1;
                  if( cycle_cnt_r == STROB_POS )
                  begin
                    state_r <= state_r << 1;
                    if ( !serial_line_ones_a && !serial_line_zeroes_a ) //Если стоп-бит
                    begin
                      if( bit_cnt_r[5:0] == config_r[6:1] ) //Проверяем количество принятых разрядов
                      begin
                        status_r[0] <= 0; //word length ok
                        status_r[1] <= 0; //receiving process ended
                        status_r[2] <= 0; //as word correctly received, no noise on inout lines
                        status_r[3] <= 1; //word received

                        if( (parity_zeroes || !parity_ones ) && config_r[0] )  buffered_data_r <= 0;
                        else  buffered_data_r <= shift_data_r;
                      end
                      else begin
                        status_r[0] <= 1; //word length fail
                        status_r[1] <= 0; //receiving process ended
                        status_r[2] <= 0; //as word correctly received, no noise on inout lines
                        status_r[3] <= 0; //word is not received
                      end

                      if( !parity_zeroes && parity_ones ) status_r[4] <= 0; //parity ok
                      else status_r[4] <= 1; //parity check fail
                    end
                    else 
                    begin
                      bit_cnt_r <= bit_cnt_r + 1;
                      if ( !serial_line_ones_a ) //Если единичка
                        begin
                          shift_data_r <= ( shift_data_r >> 1 ) | 32'h8000_0000; //Store data in high bits of register
                          parity_ones  <= parity_ones ^ 1;
                        end
                        else  //Если нолик
                          begin
                            shift_data_r  <= ( shift_data_r >> 1 ) & 32'h7FFF_FFFF;
                            parity_zeroes <= parity_zeroes ^ 1;
                          end
                    end
                  end
                end    
      5'b00100: begin //WAITING for bit transmission end state
                  if( sl0_tmp_r[3:0] == 4'h0 && sl1_tmp_r[3:0] == 4'h0 ) begin //IF we are here after STOP bit detection
                    parity_zeroes <= 0;
                    parity_ones   <= 1;
                    shift_data_r  <= 0;
                    bit_cnt_r     <= 0;
                  end

                  if( sl0_tmp_r[7:0] == 8'hFF && sl1_tmp_r[7:0] == 8'hFF )
                  begin
                    state_r <= 5'b00001; //go to the IDLE state
                    cycle_cnt_r <= 0;
                    status_r[1] <= 1; //Receiving going
                  end
                  else begin
                    cycle_cnt_r <= cycle_cnt_r + 1;
                    if( cycle_cnt_r >= 32 ) status_r[5] <= 1; //level error on line
                  end
                end
      default: state_r <= 5'b00001;
    endcase
  end
  else begin //TRANSMITTER routine
    state_r <= 5'b00001;
  end

end

endmodule

bench/hdl/tb_SL.v
`timescale 1ns / 100ps

module sl_rt_tb;

reg reset;       // Common asycnhronous reset
reg clk;
// reg clk;         // Crystal input
//reg sl00;
//reg sl10;
// reg p0;
// reg p1;
parameter tck = 10; // clock tick
reg sl0;
reg sl1;


SL_transiever dut(reset, clk, sl0, sl1);

//Error injection parameters
reg ei_data_sl0;
reg ei_data_sl1;
reg ei_quantity;
reg ei_parity;
reg ei_fh;  //freq high
reg ei_fl;  //freq low
reg ei_noise_sl0;
reg ei_noise_sl1;


parameter pause_between_words = 0;
parameter value_of_pause = 160; //in clock cycles
parameter word_legth_min = 8;
parameter word_length_max = 32;
parameter word_length_incr = 1;

reg parity0;
reg parity1;

reg fl_ei_data_sl0; //
reg fl_ei_data_sl1;//
reg fl_ei_quantity;
reg fl_ei_fh;  //freq high
reg fl_ei_fl;  //freq low
reg fl_ei_noise_sl0;//
reg fl_ei_noise_sl1;//



//Other parameters
parameter reset_after_each_word = 0;
parameter start_word = 0;
parameter finish_word = 32'hFFFF_FFFF;
parameter increment_word = 8'h1E;


integer var = 0;
integer i = 0;
integer word = 0;
integer ini_word = 0;

always #(tck/2) clk <= ~clk; // clocking device

initial begin
  $dumpfile("sl_rt.vcd");
  $dumpvars(0, dut);
  $monitor($stime,, reset,, clk,,, sl0, sl1); 
end

// testbench actions
initial 
begin
  clk   = 0; 
  reset = 0;
  sl0   = 0;
  sl1   = 0;
  #(tck*10);
  reset = 1;
  #(tck*2);

  repeat ( 32 ) begin








  begin
    ini_word = $urandom_range(0,16'hFFFF);
    word = ini_word;
    ei_data_sl0   = $urandom_range(0,1);
    ei_data_sl1   = $urandom_range(0,1);
    ei_quantity   = $urandom_range(0,1);
    ei_parity     = $urandom_range(0,1);
    ei_fh         = $urandom_range(0,1);  //freq high
    ei_fl         = $urandom_range(0,1);  //freq low
    ei_noise_sl0  = $urandom_range(0,1);
    ei_noise_sl1  = $urandom_range(0,1);

    fl_ei_data_sl0 = 0; //
    fl_ei_data_sl1 = 0;//
    fl_ei_quantity = 0;
    fl_ei_fh = 0;  //freq high
    fl_ei_fl = 0;  //freq low
    fl_ei_noise_sl0 = 0;//
    fl_ei_noise_sl1 = 0;//
    sl0 = 1;
    sl1 = 1;
    parity0  = 0;
    parity1  = 0;
    #(tck*16);

      for( i = word_legth_min; i <= word_length_max; i = i + word_length_incr ) begin
        for( var = 0; var < i; var = var + 1) begin
          if( word & 1 ) begin

            sl1 = 0;
            parity1 = parity1 ^ 1;
            #(tck*16);
            sl1 = 1;
            #(tck*8);

            if( !fl_ei_data_sl1 && ei_data_sl1 ) begin
              sl1 = 0;
              #(tck*4);
              sl1 = 1;
              #(tck*4);
              fl_ei_data_sl0 = 1;
            end else if( !fl_ei_noise_sl1 && ei_noise_sl1 ) begin
              sl1 = 0;
              #(tck*1);
              sl1 = 1;
              #(tck*7);
              fl_ei_noise_sl1 = 1;
            end
            else #(tck*8);

          end
          else begin
            sl0 = 0;
            parity0 = parity0 ^ 1;
            #(tck*16);
            sl0 = 1;
            #(tck*4);

            if( !fl_ei_data_sl0 && ei_data_sl0 ) begin
              sl0 = 0;
              #(tck*4);
              sl0 = 1;
              #(tck*4);
              fl_ei_data_sl0 = 1;
            end
            else if( !fl_ei_noise_sl0 && ei_noise_sl0 ) begin
              sl0 = 0;
              #(tck*1);
              sl0 = 1;
              #(tck*7);
              fl_ei_noise_sl0 = 1;
            end
            else #(tck*8);

          end
          word = word >> 1;
        end

        // add parity bit
        if( parity1 && ei_parity ) begin
          sl0 = 0;
          #(tck*16);
          sl0 = 1;
          #(tck*16);
        end
        else begin
          sl1 = 0;
          #(tck*16);
          sl1 = 1;
          #(tck*16);
        end

        // add stop bit
        sl1 = 0;
        sl0 = 0;
        #(tck*16);
        sl0 = 1;
        sl1 = 1;
        #(tck*16);

        //add delay after word
        #(tck*160);


    end
  end

end



end

endmodule

sim/sl_rt.vcd
$date
	Tue Oct 10 13:28:10 2017
$end
$version
	ModelSim Version 10.5
$end
$timescale
	100ps
$end

$scope module sl_rt_tb $end

$scope module dut $end
$var parameter 32 ! STROB_POS $end
$var wire 1 " rst_n $end
$var wire 1 # clk $end
$var wire 1 $ serial_line_zeroes_a $end
$var wire 1 % serial_line_ones_a $end
$var reg 16 & sl0_tmp_r [15:0] $end
$var reg 16 ' sl1_tmp_r [15:0] $end
$var reg 32 ( shift_data_r [31:0] $end
$var reg 6 ) cycle_cnt_r [5:0] $end
$var reg 6 * bit_cnt_r [5:0] $end
$var reg 5 + state_r [4:0] $end
$var reg 32 , buffered_data_r [31:0] $end
$var reg 64 - data_to_send_r [63:0] $end
$var reg 16 . config_r [15:0] $end
$var reg 16 / status_r [15:0] $end
$var reg 1 0 parity_ones $end
$var reg 1 1 parity_zeroes $end
$upscope $end
$upscope $end
$enddefinitions $end
#0
$dumpvars
bx &
bx '
bx (
bx )
bx *
bx +
bx ,
bx -
bx .
bx /
x0
x1
b1000 !
0%
0$
0#
0"
$end
#50
1#
b1010101010101010 &
b1010101010101010 '
b0 (
b0 )
b0 *
b1 +
b0 ,
b0 -
b100000 .
b0 /
01
10
#100
0#
#150
1#
b101010101010100 &
b101010101010100 '
#200
0#
#250
1#
b1010101010101010 &
b1010101010101010 '
b1010101010101000 &
b1010101010101000 '
#300
0#
#350
1#
b1010101010101010 &
b1010101010101010 '
b101010101010000 &
b101010101010000 '
#400
0#
#450
1#
b1010101010101010 &
b1010101010101010 '
b1010101010100000 &
b1010101010100000 '
#500
0#
#550
1#
b1010101010101010 &
b1010101010101010 '
b101010101000000 &
b101010101000000 '
#600
0#
#650
1#
b1010101010101010 &
b1010101010101010 '
b1010101010000000 &
b1010101010000000 '
#700
0#
#750
1#
b1010101010101010 &
b1010101010101010 '
b101010100000000 &
b101010100000000 '
#800
0#
#850
1#
b1010101010101010 &
b1010101010101010 '
b1010101000000000 &
b1010101000000000 '
#900
0#
#950
1#
b1010101010101010 &
b1010101010101010 '
b101010000000000 &
b101010000000000 '
#1000
1"
0#
#1050
1#
b1010100000000000 &
b1010100000000000 '
#1100
0#
#1150
1#
b101000000000000 &
b101000000000000 '
#1200
1$
1%
0#
#1250
1#
b1010000000000001 &
b1010000000000001 '
#1300
0#
#1350
1#
b100000000000011 &
b100000000000011 '
#1400
0#
#1450
1#
b1000000000000111 &
b1000000000000111 '
#1500
0#
#1550
1#
b1111 &
b1111 '
#1600
0#
#1650
1#
b11111 &
b11111 '
#1700
0#
#1750
1#
b111111 &
b111111 '
#1800
0#
#1850
1#
b1111111 &
b1111111 '
#1900
0#
#1950
1#
b11111111 &
b11111111 '
#2000
0#
#2050
1#
b111111111 &
b111111111 '
#2100
0#
#2150
1#
b1111111111 &
b1111111111 '
#2200
0#
#2250
1#
b11111111111 &
b11111111111 '
#2300
0#
#2350
1#
b111111111111 &
b111111111111 '
#2400
0#
#2450
1#
b1111111111111 &
b1111111111111 '
#2500
0#
#2550
1#
b11111111111111 &
b11111111111111 '
#2600
0#
#2650
1#
b111111111111111 &
b111111111111111 '
#2700
0#
#2750
1#
b1111111111111111 &
b1111111111111111 '
#2800
0$
0#
#2850
1#
b1111111111111110 &
#2900
0#
#2950
1#
b1111111111111100 &
#3000
0#
#3050
1#
b1111111111111000 &
#3100
0#
#3150
1#
b1111111111110000 &
#3200
0#
#3250
1#
b1111111111100000 &
b10 +
b11 )
b10 /
#3300
0#
#3350
1#
b1111111111000000 &
b100 )
#3400
0#
#3450
1#
b1111111110000000 &
b101 )
#3500
0#
#3550
1#
b1111111100000000 &
b110 )
#3600
0#
#3650
1#
b1111111000000000 &
b111 )
#3700
0#
#3750
1#
b1111110000000000 &
b1000 )
#3800
0#
#3850
1#
b1111100000000000 &
b1001 )
b100 +
b1 *
11
#3900
0#
#3950
1#
b1111000000000000 &
b1010 )
#4000
0#
#4050
1#
b1110000000000000 &
b1011 )
#4100
0#
#4150
1#
b1100000000000000 &
b1100 )
#4200
0#
#4250
1#
b1000000000000000 &
b1101 )
#4300
0#
#4350
1#
b0 &
b1110 )
#4400
1$
0#
#4450
1#
b1 &
b1111 )
#4500
0#
#4550
1#
b11 &
b10000 )
#4600
0#
#4650
1#
b111 &
b10001 )
#4700
0#
#4750
1#
b1111 &
b10010 )
#4800
0$
0#
#4850
1#
b11110 &
b10011 )
#4900
1$
0#
#4950
1#
b111101 &
b10100 )
#5000
0#
#5050
1#
b1111011 &
b10101 )
#5100
0#
#5150
1#
b11110111 &
b10110 )
#5200
0#
#5250
1#
b111101111 &
b10111 )
#5300
0#
#5350
1#
b1111011111 &
b11000 )
#5400
0#
#5450
1#
b11110111111 &
b11001 )
#5500
0#
#5550
1#
b111101111111 &
b11010 )
#5600
0%
0#
#5650
1#
b1111011111111 &
b1111111111111110 '
b11011 )
#5700
0#
#5750
1#
b11110111111111 &
b1111111111111100 '
b11100 )
#5800
0#
#5850
1#
b111101111111111 &
b1111111111111000 '
b11101 )
#5900
0#
#5950
1#
b1111011111111111 &
b1111111111110000 '
b11110 )
#6000
0#
#6050
1#
b1110111111111111 &
b1111111111100000 '
b11111 )
#6100
0#
#6150
1#
b1101111111111111 &
b1111111111000000 '
b100000 )
#6200
0#
#6250
1#
b1011111111111111 &
b1111111110000000 '
b100001 )
b100010 /
#6300
0#
#6350
1#
b111111111111111 &
b1111111100000000 '
b100010 )
#6400
0#
#6450
1#
b1111111111111111 &
b1111111000000000 '
b100011 )
#6500
0#
#6550
1#
b1111110000000000 '
b100100 )
#6600
0#
#6650
1#
b1111100000000000 '
b100101 )
#6700
0#
#6750
1#
b1111000000000000 '
b100110 )
#6800
0#
#6850
1#
b1110000000000000 '
b100111 )
#6900
0#
#6950
1#
b1100000000000000 '
b101000 )
#7000
0#
#7050
1#
b1000000000000000 '
b101001 )
#7100
0#
#7150
1#
b0 '
b101010 )
#7200
1%
0#
#7250
1#
b1 '
b101011 )
#7300
0#
#7350
1#
b11 '
b101100 )
#7400
0#
#7450
1#
b111 '
b101101 )
#7500
0#
#7550
1#
b1111 '
b101110 )
#7600
0#
#7650
1#
b11111 '
b101111 )
#7700
0#
#7750
1#
b111111 '
b110000 )
#7800
0#
#7850
1#
b1111111 '
b110001 )
#7900
0#
#7950
1#
b11111111 '
b110010 )
#8000
0%
0#
#8050
1#
b111111110 '
b1 +
b0 )
#8100
1%
0#
#8150
1#
b1111111101 '
#8200
0#
#8250
1#
b11111111011 '
b100110 /
#8300
0#
#8350
1#
b111111110111 '
b100010 /
#8400
0#
#8450
1#
b1111111101111 '
#8500
0#
#8550
1#
b11111111011111 '
#8600
0#
#8650
1#
b111111110111111 '
#8700
0#
#8750
1#
b1111111101111111 '
#8800
0$
0#
#8850
1#
b1111111111111110 &
b1111111011111111 '
#8900
0#
#8950
1#
b1111111111111100 &
b1111110111111111 '
#9000
0#
#9050
1#
b1111111111111000 &
b1111101111111111 '
#9100
0#
#9150
1#
b1111111111110000 &
b1111011111111111 '
#9200
0#
#9250
1#
b1111111111100000 &
b1110111111111111 '
b10 +
b11 )
b10 /
#9300
0#
#9350
1#
b1111111111000000 &
b1101111111111111 '
b100 )
#9400
0#
#9450
1#
b1111111110000000 &
b1011111111111111 '
b101 )
#9500
0#
#9550
1#
b1111111100000000 &
b111111111111111 '
b110 )
#9600
0#
#9650
1#
b1111111000000000 &
b1111111111111111 '
b111 )
#9700
0#
#9750
1#
b1111110000000000 &
b1000 )
#9800
0#
#9850
1#
b1111100000000000 &
b1001 )
b100 +
b10 *
01
#9900
0#
#9950
1#
b1111000000000000 &
b1010 )
#10000
0#
#10050
1#
b1110000000000000 &
b1011 )
#10100
0#
#10150
1#
b1100000000000000 &
b1100 )
#10200
0#
#10250
1#
b1000000000000000 &
b1101 )
#10300
0#
#10350
1#
b0 &
b1110 )
#10400
1$
0#
#10450
1#
b1 &
b1111 )
#10500
0#
#10550
1#
b11 &
b10000 )
#10600
0#
#10650
1#
b111 &
b10001 )
#10700
0#
#10750
1#
b1111 &
b10010 )
#10800
0#
#10850
1#
b11111 &
b10011 )
#10900
0#
#10950
1#
b111111 &
b10100 )
#11000
0#
#11050
1#
b1111111 &
b10101 )
#11100
0#
#11150
1#
b11111111 &
b10110 )
#11200
0#
#11250
1#
b111111111 &
b1 +
b0 )
#11300
0#
#11350
1#
b1111111111 &
#11400
0#
#11450
1#
b11111111111 &
#11500
0#
#11550
1#
b111111111111 &
#11600
0$
0#
#11650
1#
b1111111111110 &
#11700
0#
#11750
1#
b11111111111100 &
#11800
0#
#11850
1#
b111111111111000 &
#11900
0#
#11950
1#
b1111111111110000 &
#12000
0#
#12050
1#
b1111111111100000 &
b10 +
b11 )
#12100
0#
#12150
1#
b1111111111000000 &
b100 )
#12200
0#
#12250
1#
b1111111110000000 &
b101 )
#12300
0#
#12350
1#
b1111111100000000 &
b110 )
#12400
0#
#12450
1#
b1111111000000000 &
b111 )
#12500
0#
#12550
1#
b1111110000000000 &
b1000 )
#12600
0#
#12650
1#
b1111100000000000 &
b1001 )
b100 +
b11 *
11
#12700
0#
#12750
1#
b1111000000000000 &
b1010 )
#12800
0#
#12850
1#
b1110000000000000 &
b1011 )
#12900
0#
#12950
1#
b1100000000000000 &
b1100 )
#13000
0#
#13050
1#
b1000000000000000 &
b1101 )
#13100
0#
#13150
1#
b0 &
b1110 )
#13200
1$
0#
#13250
1#
b1 &
b1111 )
#13300
0#
#13350
1#
b11 &
b10000 )
#13400
0#
#13450
1#
b111 &
b10001 )
#13500
0#
#13550
1#
b1111 &
b10010 )
#13600
0#
#13650
1#
b11111 &
b10011 )
#13700
0#
#13750
1#
b111111 &
b10100 )
#13800
0#
#13850
1#
b1111111 &
b10101 )
#13900
0#
#13950
1#
b11111111 &
b10110 )
#14000
0#
#14050
1#
b111111111 &
b1 +
b0 )
#14100
0#
#14150
1#
b1111111111 &
#14200
0#
#14250
1#
b11111111111 &
#14300
0#
#14350
1#
b111111111111 &
#14400
0%
0#
#14450
1#
b1111111111111 &
b1111111111111110 '
#14500
0#
#14550
1#
b11111111111111 &
b1111111111111100 '
#14600
0#
#14650
1#
b111111111111111 &
b1111111111111000 '
#14700
0#
#14750
1#
b1111111111111111 &
b1111111111110000 '
#14800
0#
#14850
1#
b1111111111100000 '
b10 +
b11 )
#14900
0#
#14950
1#
b1111111111000000 '
b100 )
#15000
0#
#15050
1#
b1111111110000000 '
b101 )
#15100
0#
#15150
1#
b1111111100000000 '
b110 )
#15200
0#
#15250
1#
b1111111000000000 '
b111 )
#15300
0#
#15350
1#
b1111110000000000 '
b1000 )
#15400
0#
#15450
1#
b1111100000000000 '
b1001 )
b100 +
b100 *
b10000000000000000000000000000000 (
00
#15500
0#
#15550
1#
b1111000000000000 '
b1010 )
#15600
0#
#15650
1#
b1110000000000000 '
b1011 )
#15700
0#
#15750
1#
b1100000000000000 '
b1100 )
#15800
0#
#15850
1#
b1000000000000000 '
b1101 )
#15900
0#
#15950
1#
b0 '
b1110 )
#16000
1%
0#
#16050
1#
b1 '
b1111 )
#16100
0#
#16150
1#
b11 '
b10000 )
#16200
0#
#16250
1#
b111 '
b10001 )
#16300
0#
#16350
1#
b1111 '
b10010 )
#16400
0#
#16450
1#
b11111 '
b10011 )
#16500
0#
#16550
1#
b111111 '
b10100 )
#16600
0#
#16650
1#
b1111111 '
b10101 )
#16700
0#
#16750
1#
b11111111 '
b10110 )
#16800
0#
#16850
1#
b111111111 '
b1 +
b0 )
#16900
0#
#16950
1#
b1111111111 '
#17000
0#
#17050
1#
b11111111111 '
#17100
0#
#17150
1#
b111111111111 '
#17200
0#
#17250
1#
b1111111111111 '
#17300
0#
#17350
1#
b11111111111111 '
#17400
0#
#17450
1#
b111111111111111 '
#17500
0#
#17550
1#
b1111111111111111 '
#17600
0%
0#
#17650
1#
b1111111111111110 '
#17700
0#
#17750
1#
b1111111111111100 '
#17800
0#
#17850
1#
b1111111111111000 '
#17900
0#
#17950
1#
b1111111111110000 '
#18000
0#
#18050
1#
b1111111111100000 '
b10 +
b11 )
#18100
0#
#18150
1#
b1111111111000000 '
b100 )
#18200
0#
#18250
1#
b1111111110000000 '
b101 )
#18300
0#
#18350
1#
b1111111100000000 '
b110 )
#18400
0#
#18450
1#
b1111111000000000 '
b111 )
#18500
0#
#18550
1#
b1111110000000000 '
b1000 )
#18600
0#
#18650
1#
b1111100000000000 '
b1001 )
b100 +
b101 *
b11000000000000000000000000000000 (
10
#18700
0#
#18750
1#
b1111000000000000 '
b1010 )
#18800
0#
#18850
1#
b1110000000000000 '
b1011 )
#18900
0#
#18950
1#
b1100000000000000 '
b1100 )
#19000
0#
#19050
1#
b1000000000000000 '
b1101 )
#19100
0#
#19150
1#
b0 '
b1110 )
#19200
1%
0#
#19250
1#
b1 '
b1111 )
#19300
0#
#19350
1#
b11 '
b10000 )
#19400
0#
#19450
1#
b111 '
b10001 )
#19500
0#
#19550
1#
b1111 '
b10010 )
#19600
0#
#19650
1#
b11111 '
b10011 )
#19700
0#
#19750
1#
b111111 '
b10100 )
#19800
0#
#19850
1#
b1111111 '
b10101 )
#19900
0#
#19950
1#
b11111111 '
b10110 )
#20000
0#
#20050
1#
b111111111 '
b1 +
b0 )
#20100
0#
#20150
1#
b1111111111 '
#20200
0#
#20250
1#
b11111111111 '
#20300
0#
#20350
1#
b111111111111 '
#20400
0#
#20450
1#
b1111111111111 '
#20500
0#
#20550
1#
b11111111111111 '
#20600
0#
#20650
1#
b111111111111111 '
#20700
0#
#20750
1#
b1111111111111111 '
#20800
0%
0#
#20850
1#
b1111111111111110 '
#20900
0#
#20950
1#
b1111111111111100 '
#21000
0#
#21050
1#
b1111111111111000 '
#21100
0#
#21150
1#
b1111111111110000 '
#21200
0#
#21250
1#
b1111111111100000 '
b10 +
b11 )
#21300
0#
#21350
1#
b1111111111000000 '
b100 )
#21400
0#
#21450
1#
b1111111110000000 '
b101 )
#21500
0#
#21550
1#
b1111111100000000 '
b110 )
#21600
0#
#21650
1#
b1111111000000000 '
b111 )
#21700
0#
#21750
1#
b1111110000000000 '
b1000 )
#21800
0#
#21850
1#
b1111100000000000 '
b1001 )
b100 +
b110 *
b11100000000000000000000000000000 (
00
#21900
0#
#21950
1#
b1111000000000000 '
b1010 )
#22000
0#
#22050
1#
b1110000000000000 '
b1011 )
#22100
0#
#22150
1#
b1100000000000000 '
b1100 )
#22200
0#
#22250
1#
b1000000000000000 '
b1101 )
#22300
0#
#22350
1#
b0 '
b1110 )
#22400
1%
0#
#22450
1#
b1 '
b1111 )
#22500
0#
#22550
1#
b11 '
b10000 )
#22600
0#
#22650
1#
b111 '
b10001 )
#22700
0#
#22750
1#
b1111 '
b10010 )
#22800
0#
#22850
1#
b11111 '
b10011 )
#22900
0#
#22950
1#
b111111 '
b10100 )
#23000
0#
#23050
1#
b1111111 '
b10101 )
#23100
0#
#23150
1#
b11111111 '
b10110 )
#23200
0#
#23250
1#
b111111111 '
b1 +
b0 )
#23300
0#
#23350
1#
b1111111111 '
#23400
0#
#23450
1#
b11111111111 '
#23500
0#
#23550
1#
b111111111111 '
#23600
0#
#23650
1#
b1111111111111 '
#23700
0#
#23750
1#
b11111111111111 '
#23800
0#
#23850
1#
b111111111111111 '
#23900
0#
#23950
1#
b1111111111111111 '
#24000
0$
0#
#24050
1#
b1111111111111110 &
#24100
0#
#24150
1#
b1111111111111100 &
#24200
0#
#24250
1#
b1111111111111000 &
#24300
0#
#24350
1#
b1111111111110000 &
#24400
0#
#24450
1#
b1111111111100000 &
b10 +
b11 )
#24500
0#
#24550
1#
b1111111111000000 &
b100 )
#24600
0#
#24650
1#
b1111111110000000 &
b101 )
#24700
0#
#24750
1#
b1111111100000000 &
b110 )
#24800
0#
#24850
1#
b1111111000000000 &
b111 )
#24900
0#
#24950
1#
b1111110000000000 &
b1000 )
#25000
0#
#25050
1#
b1111100000000000 &
b1001 )
b100 +
b111 *
b1110000000000000000000000000000 (
01
#25100
0#
#25150
1#
b1111000000000000 &
b1010 )
#25200
0#
#25250
1#
b1110000000000000 &
b1011 )
#25300
0#
#25350
1#
b1100000000000000 &
b1100 )
#25400
0#
#25450
1#
b1000000000000000 &
b1101 )
#25500
0#
#25550
1#
b0 &
b1110 )
#25600
1$
0#
#25650
1#
b1 &
b1111 )
#25700
0#
#25750
1#
b11 &
b10000 )
#25800
0#
#25850
1#
b111 &
b10001 )
#25900
0#
#25950
1#
b1111 &
b10010 )
#26000
0#
#26050
1#
b11111 &
b10011 )
#26100
0#
#26150
1#
b111111 &
b10100 )
#26200
0#
#26250
1#
b1111111 &
b10101 )
#26300
0#
#26350
1#
b11111111 &
b10110 )
#26400
0#
#26450
1#
b111111111 &
b1 +
b0 )
#26500
0#
#26550
1#
b1111111111 &
#26600
0#
#26650
1#
b11111111111 &
#26700
0#
#26750
1#
b111111111111 &
#26800
0%
0#
#26850
1#
b1111111111111 &
b1111111111111110 '
#26900
0#
#26950
1#
b11111111111111 &
b1111111111111100 '
#27000
0#
#27050
1#
b111111111111111 &
b1111111111111000 '
#27100
0#
#27150
1#
b1111111111111111 &
b1111111111110000 '
#27200
0#
#27250
1#
b1111111111100000 '
b10 +
b11 )
#27300
0#
#27350
1#
b1111111111000000 '
b100 )
#27400
0#
#27450
1#
b1111111110000000 '
b101 )
#27500
0#
#27550
1#
b1111111100000000 '
b110 )
#27600
0#
#27650
1#
b1111111000000000 '
b111 )
#27700
0#
#27750
1#
b1111110000000000 '
b1000 )
#27800
0#
#27850
1#
b1111100000000000 '
b1001 )
b100 +
b1000 *
b10111000000000000000000000000000 (
10
#27900
0#
#27950
1#
b1111000000000000 '
b1010 )
#28000
0#
#28050
1#
b1110000000000000 '
b1011 )
#28100
0#
#28150
1#
b1100000000000000 '
b1100 )
#28200
0#
#28250
1#
b1000000000000000 '
b1101 )
#28300
0#
#28350
1#
b0 '
b1110 )
#28400
1%
0#
#28450
1#
b1 '
b1111 )
#28500
0#
#28550
1#
b11 '
b10000 )
#28600
0#
#28650
1#
b111 '
b10001 )
#28700
0#
#28750
1#
b1111 '
b10010 )
#28800
0#
#28850
1#
b11111 '
b10011 )
#28900
0#
#28950
1#
b111111 '
b10100 )
#29000
0#
#29050
1#
b1111111 '
b10101 )
#29100
0#
#29150
1#
b11111111 '
b10110 )
#29200
0#
#29250
1#
b111111111 '
b1 +
b0 )
#29300
0#
#29350
1#
b1111111111 '
#29400
0#
#29450
1#
b11111111111 '
#29500
0#
#29550
1#
b111111111111 '
#29600
0#
#29650
1#
b1111111111111 '
#29700
0#
#29750
1#
b11111111111111 '
#29800
0#
#29850
1#
b111111111111111 '
#29900
0#
#29950
1#
b1111111111111111 '
#30000
0%
0$
0#
#30050
1#
b1111111111111110 &
b1111111111111110 '
#30100
0#
#30150
1#
b1111111111111100 &
b1111111111111100 '
#30200
0#
#30250
1#
b1111111111111000 &
b1111111111111000 '
#30300
0#
#30350
1#
b1111111111110000 &
b1111111111110000 '
#30400
0#
#30450
1#
b1111111111100000 &
b1111111111100000 '
b10 +
b11 )
#30500
0#
#30550
1#
b1111111111000000 &
b1111111111000000 '
b100 )
#30600
0#
#30650
1#
b1111111110000000 &
b1111111110000000 '
b101 )
#30700
0#
#30750
1#
b1111111100000000 &
b1111111100000000 '
b110 )
#30800
0#
#30850
1#
b1111111000000000 &
b1111111000000000 '
b111 )
#30900
0#
#30950
1#
b1111110000000000 &
b1111110000000000 '
b1000 )
#31000
0#
#31050
1#
b1111100000000000 &
b1111100000000000 '
b1001 )
b100 +
b11 /
b1 /
#31100
0#
#31150
1#
b1111000000000000 &
b1111000000000000 '
b0 (
b0 *
b1010 )
#31200
0#
#31250
1#
b1110000000000000 &
b1110000000000000 '
b1011 )
#31300
0#
#31350
1#
b1100000000000000 &
b1100000000000000 '
b1100 )
#31400
0#
#31450
1#
b1000000000000000 &
b1000000000000000 '
b1101 )
#31500
0#
#31550
1#
b0 &
b0 '
b1110 )
#31600
1$
1%
0#
#31650
1#
b1 &
b1 '
b1111 )
#31700
0#
#31750
1#
b11 &
b11 '
b10000 )
#31800
0#
#31850
1#
b111 &
b111 '
b10001 )
#31900
0#
#31950
1#
b1111 &
b1111 '
b10010 )
#32000
0#
#32050
1#
b11111 &
b11111 '
b10011 )
#32100
0#
#32150
1#
b111111 &
b111111 '
b10100 )
#32200
0#
#32250
1#
b1111111 &
b1111111 '
b10101 )
#32300
0#
#32350
1#
b11111111 &
b11111111 '
b10110 )
#32400
0#
#32450
1#
b111111111 &
b111111111 '
b1 +
b0 )
b11 /
#32500
0#
#32550
1#
b1111111111 &
b1111111111 '
#32600
0#
