rtl/SL.v
module SL_transiever (
  //Common signals
  input wire rst_n,
  input wire clk, //16MHz

  // SL related signals
  input wire serial_line_zeroes_a,
  input wire serial_line_ones_a,
  // output wire sl0,
  // output wire sl1,

 // APB related signals
 //Master APB signals
  input wire pclk_a,
  input wire preset_n_a,
  input wire [ 7:0] paddr_a, //let's pretend that this is HIGHER bits of address space, i mean sys_addr[31:24].
  //input wire [ 3:0] pstrb_a, //remove this also
  //input wire pprot_a[2:0], //dont need this also
  input wire psel_a, //Cant work only with address checking cause of bi-directional data bus
  input wire penable_a,
  input wire pwrite_a,
  //Slave APB signals
  //output wire pready_a, //lets think we dont need this signal cause we'll make fixed two cycles access
  //output wire pslverr_a, //all status info there is in `status` register which is freely accessed any time
  inout wire [31:0] pdata_a

    );

parameter STROB_POS = 8;
parameter CONFIG_ADDRESS  = 0'b0001;
parameter DATA_ADDRESS_WR = 0'b0010;
parameter DATA_ADDRESS_R  = 0'b0100;
parameter STATUS_ADDRESS  = 0'b1000;

// parameter S0 = 5'b0_0000,
//           S1 = 5'b0_0001,
//           S2 = 5'b0_0010,
//           S3 = 5'b0_0011,
//           S4 = 5'b0_0100,
//           S5 = 5'b0_0101,
//           S6 = 5'b0_0110,
//           S7 = 5'b0_0111,
//           S8 = 5'b0_1000,
//           S9 = 5'b0_1001,
//           S10= 5'b0_1010;

parameter BIT_WAIT_FLUSH    = 0, //S0
          BIT_WAIT_NO_FLUSH = 1, //S1
          BIT_DETECTED      = 2, //S2
          STOP_BIT          = 3, //S3
          ONE_BIT           = 4, //S4
          ZERO_BIT          = 5, //S5
          GOT_WORD          = 6, //S6
          PAR_ERR           = 7, //S7
          LEN_ERR           = 8, //S8
          LEV_ERR           = 9, //S9
          WAIT_BIT_END     = 10; //S10

reg [ 10:0] state_r, next_r; //RECEIVER MODE: 0 - idle, 1 - receiveing started, 1a - bit detected, 1b - no bit, 1c - stop bit
                    //TRANSMITTER MODE: 0 - idle, 1 - sending a word



//APB resynchronisation registers
reg [ 7:0] sync1_paddr_r;
reg [31:0] sync1_pdata_r;
reg [ 7:0] sync1_misc_r; //we DO NOT sync 'pclk' and 'preset_n'

reg [ 7:0] in_paddr_r;
reg [31:0] in_pdata_r;
reg [ 7:0] in_misc_r;

//wire {pprot, psel, penable, pwrite, pstrb[3:0]};

//assign {pprot, psel, penable, pwrite, pstrb[3:0]} = in_misc_r[7:0];


// SL receiver related registers
reg [15:0] sl0_tmp_r; //shift regs to temporary store input sequence
reg [15:0] sl1_tmp_r;
reg [32:0] shift_data_r;
reg [ 5:0] cycle_cnt_r;
reg [ 5:0] bit_cnt_r;


reg [31:0] buffered_data_r;
reg [31:0] data_to_send_r;
reg [15:0] config_r; //[0] - parity check, [6:1] - bit cnt(8-32bits), [7] - rxtx mode, [8] - IRQ mode ####address on config_r is 0 (zero)
parameter PCE = 0;
reg [15:0] status_r; //[0] - word length fail, [1] - word receiveing process going, [2] - empty
                    //[3] - word received, [4] - parity error, [5] - level error on line,
reg parity_ones;
reg parity_zeroes;

//Synchronisation registers to read from corresponding registers via APB
reg [31:0] sync1_buffered_data_r;
reg [15:0] sync1_config_r;
reg [15:0] sync1_status_r;

reg [31:0] apb_buffered_data_r;
reg [15:0] apb_config_r;
reg [15:0] apb_status_r;
reg [31:0] apb_muxed_out_r;

//Synchronisation registers to write to corresponding registers via APB
reg [31:0] apb2sl_sync1_data_to_send_r;
reg [15:0] apb2sl_sync1_config_r;

reg [31:0] apb2sl_sync2_data_to_send_r;
reg [15:0] apb2sl_sync2_config_r;



reg [2:0] apb_state; //001 - IDLE, 010 - SETUP, 100 - ACCESS

wire bit_ended;
wire bit_started;


assign pdata_a = ( penable_a && psel_a && !pwrite_a ) ? apb_muxed_out_r : 32'bz;
assign bit_ended   = (sl0_tmp_r[7:0] == 8'hFF && sl1_tmp_r[7:0] == 8'hFF) ? 1 : 0;
assign bit_started = (sl0_tmp_r[15:12] == 4'hF && sl0_tmp_r[3:0] == 4'h0) || (sl1_tmp_r[15:12] == 4'hF && sl1_tmp_r[3:0] == 4'h0) ? 1 : 0;




always @(posedge clk or negedge rst_n or negedge preset_n_a) begin
  if( !rst_n || !preset_n_a ) begin
    state_r <= 10'b0;
    state_r[BIT_WAIT_FLUSH] <= 1'b1;
  end
  else  state_r <= next_r;
end



//always @(state_r or serial_line_ones_a or serial_line_zeroes_a or cycle_cnt_r or bit_cnt_r or bit_ended or parity_ones or parity_zeroes or config_r[PCE] or clk) begin
always @* begin
  next_r = 10'b0;
  case( 1'b1 ) // synopsys parallel_case
  //were (state_r), but here we using reverse case to make sure it compare only one bit in a vector
    state_r[   BIT_WAIT_FLUSH]: if( bit_started && bit_cnt_r[5:0] == 6'b00_0000 )                                   next_r[BIT_WAIT_NO_FLUSH] = 1'b1; //S1 - wait state w/ flush
                                else if( bit_started )                                                              next_r[     BIT_DETECTED] = 1'b1; //S0 - wait state w/o flush
                                else                                                                                next_r[   BIT_WAIT_FLUSH] = 1'b1;
    state_r[BIT_WAIT_NO_FLUSH]:                                                                                     next_r[     BIT_DETECTED] = 1'b1;
    state_r[     BIT_DETECTED]: if( cycle_cnt_r < STROB_POS )                                                       next_r[     BIT_DETECTED] = 1'b1; //
                                else if( !serial_line_ones_a && !serial_line_zeroes_a && cycle_cnt_r == STROB_POS ) next_r[         STOP_BIT] = 1'b1; //Go to STOP bit routine
                                else if( !serial_line_ones_a &&  serial_line_zeroes_a && cycle_cnt_r == STROB_POS ) next_r[          ONE_BIT] = 1'b1; //Go to ONE bit routine
                                else if(  serial_line_ones_a && !serial_line_zeroes_a && cycle_cnt_r == STROB_POS ) next_r[         ZERO_BIT] = 1'b1; //Go to ZERO bit routine
                                else                                                                                next_r[          LEV_ERR] = 1'b1; //Error condition, go to S9
    state_r[        STOP_BIT]: if( bit_cnt_r[5:0] == config_r[6:1] + 1 && (!config_r[PCE] | !(parity_ones | parity_zeroes)) )      next_r[GOT_WORD] = 1'b1; //Go to data ok routine
                               else if( bit_cnt_r[5:0] == config_r[6:1] + 1  && config_r[PCE] &&  (parity_ones | parity_zeroes) )  next_r[ PAR_ERR] = 1'b1;//Go to PEF routine
                               else                                                                                                next_r[ LEN_ERR] = 1'b1; //Go to WLF routine
    state_r[         ONE_BIT]: next_r[BIT_WAIT_FLUSH] = 1'b1;
    state_r[        ZERO_BIT]: next_r[BIT_WAIT_FLUSH] = 1'b1;
    state_r[        GOT_WORD]: next_r[BIT_WAIT_FLUSH] = 1'b1;
    state_r[         PAR_ERR]: next_r[BIT_WAIT_FLUSH] = 1'b1;
    state_r[         LEN_ERR]: next_r[BIT_WAIT_FLUSH] = 1'b1;
    state_r[         LEV_ERR]: next_r[BIT_WAIT_FLUSH] = 1'b1;
    state_r[    WAIT_BIT_END]: if( bit_ended ) next_r[BIT_WAIT_FLUSH] = 1'b1;
                                 else          next_r[  WAIT_BIT_END] = 1'b1;
  endcase
end


always @(posedge clk or negedge rst_n or negedge preset_n_a) begin
  if( !rst_n | !preset_n_a ) begin
    sl0_tmp_r[15:0]       <= 16'hAAAA;
    sl1_tmp_r[15:0]       <= 16'hAAAA;
    shift_data_r[32:0]    <= 0;
    cycle_cnt_r[5:0]      <= 0;
    bit_cnt_r[5:0]        <= 0;
    buffered_data_r[31:0] <= 0;
    data_to_send_r[31:0]  <= 0;
    config_r[15:0]        <= 16'h0020;
    status_r[15:0]        <= 0;
    parity_zeroes         <= 0;
    parity_ones           <= 1;
    apb2sl_sync1_data_to_send_r <= 32'h0000_0000;
    apb2sl_sync1_config_r       <= 16'h0000;
    apb2sl_sync2_data_to_send_r <= 32'h0000_0000;
    apb2sl_sync2_config_r       <= 16'h0000;
    next_r <= 0;


  end else begin
      sl0_tmp_r[15:0] <= ( sl0_tmp_r << 1 ) | serial_line_zeroes_a ;
      sl1_tmp_r[15:0] <= ( sl1_tmp_r << 1 ) | serial_line_ones_a;

    //  case(next_r)
      case( 1'b1 ) // synopsys parallel_case
        next_r[BIT_WAIT_FLUSH], next_r[STOP_BIT], next_r[WAIT_BIT_END]: begin
              cycle_cnt_r <= 0;
            end
        next_r[BIT_WAIT_NO_FLUSH]: begin //wait state with flush
              status_r[15:0] <= 0;
            end
          next_r[BIT_DETECTED]: begin
              cycle_cnt_r <= cycle_cnt_r + 1;
              status_r[0] <= 0; //word length ok
              status_r[1] <= 1; //receiving process on
              status_r[3] <= 0; //Word received flag off
              status_r[4] <= 0; //no parity error atm
              status_r[5] <= 0; //no level errors on line
            end
        // S3: begin
        //
        //     end
        next_r[ONE_BIT]: begin
              shift_data_r <= ( shift_data_r >> 1 ) | ( 1 << config_r[6:1] ); //Store data in high bits of register
              parity_ones  <= parity_ones ^ 1;
              bit_cnt_r    <= bit_cnt_r + 1;
            end
        next_r[ZERO_BIT]: begin
              shift_data_r  <= ( shift_data_r >> 1 ) & ~( 1 << config_r[6:1] );
              parity_zeroes <= parity_zeroes ^ 1;
              bit_cnt_r     <= bit_cnt_r + 1;
            end
        next_r[GOT_WORD]: begin //DATA recevied correctly
              parity_zeroes <= 0;
              parity_ones   <= 1;
              shift_data_r  <= 0;
              bit_cnt_r     <= 0;
              cycle_cnt_r   <= 0;
              status_r[0]   <= 0; //word length ok
              status_r[1]   <= 0; //receiving process ended
              status_r[2]   <= 0; //as word correctly received, no noise on inout lines
              status_r[3]   <= 1; //word received
              status_r[4]   <= 0; //Dont care about parity value
              status_r[5]   <= 0; //no level errors on line
              buffered_data_r <= shift_data_r & ~( 1 << config_r[6:1] ); //Dont forget to wipeout parity bit
            end
        next_r[PAR_ERR]: begin
              parity_zeroes <= 0;
              parity_ones   <= 1;
              shift_data_r  <= 0;
              bit_cnt_r     <= 0;
              cycle_cnt_r   <= 0;
              status_r[0]   <= 0; //word length ok
              status_r[1]   <= 0; //receiving process ended
              status_r[2]   <= 0; //as word correctly received, no noise on inout lines
              status_r[3]   <= 1; //word received
              status_r[4]   <= 1; //Parity error detected
              status_r[5]   <= 0; //no level errors on line
              buffered_data_r <= 32'h0000_0000;
            end
        next_r[LEN_ERR]: begin
              parity_zeroes <= 0;
              parity_ones   <= 1;
              shift_data_r  <= 0;
              bit_cnt_r     <= 0;
              cycle_cnt_r   <= 0;
              status_r[0]   <= 1; //word length check error
              status_r[1]   <= 0; //receiving process ended
              status_r[2]   <= 0; //as word correctly received, no noise on inout lines
              status_r[3]   <= 1; //word received
              status_r[4]   <= 0; //Parity error detected
              status_r[5]   <= 0; //no level errors on line
              buffered_data_r <= 32'h0000_0000;
            end
        next_r[LEV_ERR]: begin
              parity_zeroes <= 0;
              parity_ones   <= 1;
              shift_data_r  <= 0;
              bit_cnt_r     <= 0;
              cycle_cnt_r   <= 0;
              status_r[0]   <= 0; //word length check error
              status_r[1]   <= 0; //receiving process ended
              status_r[2]   <= 0; //as word correctly received, no noise on inout lines
              status_r[3]   <= 0; //word received
              status_r[4]   <= 0; //Parity error detected
              status_r[5]   <= 1; // level errors on line
              buffered_data_r <= 32'h0000_0000;
            end
      endcase
    end
end



always @(posedge pclk_a or negedge rst_n or negedge preset_n_a) begin
  if ( !rst_n || !preset_n_a ) begin
    sync1_buffered_data_r <= 32'h0000_0000;
    sync1_config_r        <= 16'h0000;
    sync1_status_r        <= 16'h0000;

    apb_buffered_data_r   <= 32'h0000_0000;
    apb_config_r          <= 16'h0000;
    apb_status_r          <= 16'h0000;

  end
  else begin
    //First stage sync, have to do this cause we need to read data in two cycles, so data must be ready every time and all routines must work related to APB clk
    sync1_buffered_data_r <= buffered_data_r;
    sync1_config_r        <= config_r;
    sync1_status_r        <= status_r;

    //Second stage sync
    apb_buffered_data_r   <= sync1_buffered_data_r;
    apb_config_r          <= sync1_config_r;
    apb_status_r          <= sync1_status_r;

    if( psel_a && !penable_a ) begin
      if( pwrite_a ) begin // WRITE sequence
        case( paddr_a )
          CONFIG_ADDRESS:
            begin
              config_r[15:0] <= in_pdata_r[15:0];
            end
          DATA_ADDRESS_WR:
            begin
              data_to_send_r[31:0] <= in_pdata_r[31:0];
            end
          default:
            begin

            end
        endcase
      end
      else begin //READ sequence
        case( paddr_a )
          CONFIG_ADDRESS:
            begin
              apb_muxed_out_r[31:0] <= { 16'h0000, apb_config_r[15:0] };
            end
          DATA_ADDRESS_R:
            begin
              apb_muxed_out_r[31:0] <= apb_buffered_data_r[31:0];
            end
          STATUS_ADDRESS:
            begin
              apb_muxed_out_r[31:0] <= { 16'h0000, apb_status_r[15:0] };
            end
          default:
            begin
              apb_muxed_out_r[31:0] <= 32'h0000_0000;
            end
        endcase
      end
    end

  end
end


endmodule

bench/hdl/tb_SL.v
`timescale 1ns / 100ps

module sl_rt_tb;

reg reset;       // Common asycnhronous reset
reg clk;
parameter tck = 10; // clock tick
reg sl0;
reg sl1;
reg pclk;
reg preset_n;
reg [ 7:0] paddr;
reg psel; //Cant work only with address checking cause of bi-directional data bus
reg penable;
reg pwrite;
wire [31:0] pdata;


SL_transiever dut(reset, clk, sl0, sl1, clk, reset, paddr, psel, penable, pwrite, pdata);

//Error injection parameters
reg ei_data_sl0;
reg ei_data_sl1;
reg ei_quantity;
reg ei_parity;
reg ei_fh;  //freq high
reg ei_fl;  //freq low
reg ei_noise_sl0;
reg ei_noise_sl1;


parameter pause_between_words = 0;
parameter value_of_pause = 160; //in clock cycles
parameter word_legth_min = 8;
parameter word_length_max = 32;
parameter word_length_incr = 1;

reg parity0;
reg parity1;

reg fl_ei_data_sl0; //
reg fl_ei_data_sl1;//
reg fl_ei_quantity;
reg fl_ei_fh;  //freq high
reg fl_ei_fl;  //freq low
reg fl_ei_noise_sl0;//
reg fl_ei_noise_sl1;//



//Other parameters
parameter reset_after_each_word = 0;
parameter start_word = 0;
parameter finish_word = 32'hFFFF_FFFF;
parameter increment_word = 8'h1E;


int var1 = 0;
int i = 0;
int word = 0;
int ini_word = 0;

always #(tck/2) clk <= ~clk; // clocking device
always #(tck/2) pclk <= ~pclk; // clocking device

initial begin
  $dumpfile("sl_rt.vcd");
  $dumpvars(0, dut);
  $monitor($stime,, reset,, clk,,, sl0, sl1);
end

// testbench actions
initial
begin
  pclk     = 0;
  preset_n = 0;
  paddr    = 0;
  psel     = 0;
  penable  = 0;
  pwrite   = 0;


  clk   = 0;
  reset = 0;
  sl0   = 1;
  sl1   = 1;
  #(tck*10);
  reset = 1;
  preset_n = 1;
  #(tck*2);



  ini_word = 16'b1110_0011_1111_0001;
  word = ini_word;
  ei_data_sl0   = 0;
  ei_data_sl1   = 0;
  ei_quantity   = 0;
  ei_parity     = 0;
  ei_fh         = 0;  //freq high
  ei_fl         = 0;  //freq low
  ei_noise_sl0  = 0;
  ei_noise_sl1  = 0;

  fl_ei_data_sl0 = 0; //
  fl_ei_data_sl1 = 0;//
  fl_ei_quantity = 0;
  fl_ei_fh = 0;  //freq high
  fl_ei_fl = 0;  //freq low
  fl_ei_noise_sl0 = 0;//
  fl_ei_noise_sl1 = 0;//
  sl0 = 1;
  sl1 = 1;
  parity0  = 0;
  parity1  = 0;
  #(tck*16);

      i = 16;
    //for( i = word_legth_min; i <= word_length_max; i = i + word_length_incr ) begin
      for( var1 = 0; var1 < i ; var1 = var1 + 1 ) begin
        if( word & 1 ) begin

          sl1 = 0;
          parity1 = parity1 ^ 1;
          #(tck*16);
          sl1 = 1;
          #(tck*8);

          if( !fl_ei_data_sl1 && ei_data_sl1 ) begin
            sl1 = 0;
            #(tck*4);
            sl1 = 1;
            #(tck*4);
            fl_ei_data_sl0 = 1;
          end else if( !fl_ei_noise_sl1 && ei_noise_sl1 ) begin
            sl1 = 0;
            #(tck*1);
            sl1 = 1;
            #(tck*7);
            fl_ei_noise_sl1 = 1;
          end
          else #(tck*8);

        end
        else begin
          sl0 = 0;
          parity0 = parity0 ^ 1;
          #(tck*16);
          sl0 = 1;
          #(tck*4);

          if( !fl_ei_data_sl0 && ei_data_sl0 ) begin
            sl0 = 0;
            #(tck*4);
            sl0 = 1;
            #(tck*4);
            fl_ei_data_sl0 = 1;
          end
          else if( !fl_ei_noise_sl0 && ei_noise_sl0 ) begin
            sl0 = 0;
            #(tck*1);
            sl0 = 1;
            #(tck*7);
            fl_ei_noise_sl0 = 1;
          end
          else #(tck*8);

        end
        word = word >> 1;
      end

      // add parity bit
      // if( parity1 && ei_parity ) begin
      if( parity1 ) begin
        sl0 = 0;
        #(tck*16);
        sl0 = 1;
        #(tck*16);
      end
      else begin
        sl1 = 0;
        #(tck*16);
        sl1 = 1;
        #(tck*16);
      end

      // add stop bit
      sl1 = 0;
      sl0 = 0;
      #(tck*16);
      sl0 = 1;
      sl1 = 1;
      #(tck*16);

      //add delay after word
      #(tck*16);

      #(tck/2);
      //APB master read sequence
      paddr  <= 4'b0100;
      pwrite <= 0;
      psel   <= 1;
      #tck;

      penable <= 1;
      #tck;

      paddr   <= 0;
      pwrite  <= 0;
      psel    <= 0;
      penable <= 0;

      #tck;
      paddr  <= 4'b1000;
      pwrite <= 0;
      psel   <= 1;
      #tck;

      penable <= 1;
      #tck;

      paddr   <= 0;
      pwrite  <= 0;
      psel    <= 0;
      penable <= 0;


end
endmodule

sim/sl_rt.vcd
$date
	Tue Oct 17 16:56:58 2017
$end
$version
	ModelSim Version 10.5
$end
$timescale
	100ps
$end

$scope module sl_rt_tb $end

$scope module dut $end
$var parameter 32 ! STROB_POS $end
$var parameter 32 " CONFIG_ADDRESS $end
$var parameter 32 # DATA_ADDRESS_WR $end
$var parameter 32 $ DATA_ADDRESS_R $end
$var parameter 32 % STATUS_ADDRESS $end
$var parameter 32 & BIT_WAIT_FLUSH $end
$var parameter 32 ' BIT_WAIT_NO_FLUSH $end
$var parameter 32 ( BIT_DETECTED $end
$var parameter 32 ) STOP_BIT $end
$var parameter 32 * ONE_BIT $end
$var parameter 32 + ZERO_BIT $end
$var parameter 32 , GOT_WORD $end
$var parameter 32 - PAR_ERR $end
$var parameter 32 . LEN_ERR $end
$var parameter 32 / LEV_ERR $end
$var parameter 32 0 WAIT_BIT_END $end
$var parameter 32 1 PCE $end
$var wire 1 2 rst_n $end
$var wire 1 3 clk $end
$var wire 1 4 serial_line_zeroes_a $end
$var wire 1 5 serial_line_ones_a $end
$var wire 1 6 pclk_a $end
$var wire 1 7 preset_n_a $end
$var wire 1 8 paddr_a [7] $end
$var wire 1 9 paddr_a [6] $end
$var wire 1 : paddr_a [5] $end
$var wire 1 ; paddr_a [4] $end
$var wire 1 < paddr_a [3] $end
$var wire 1 = paddr_a [2] $end
$var wire 1 > paddr_a [1] $end
$var wire 1 ? paddr_a [0] $end
$var wire 1 @ psel_a $end
$var wire 1 A penable_a $end
$var wire 1 B pwrite_a $end
$var wire 1 C pdata_a [31] $end
$var wire 1 D pdata_a [30] $end
$var wire 1 E pdata_a [29] $end
$var wire 1 F pdata_a [28] $end
$var wire 1 G pdata_a [27] $end
$var wire 1 H pdata_a [26] $end
$var wire 1 I pdata_a [25] $end
$var wire 1 J pdata_a [24] $end
$var wire 1 K pdata_a [23] $end
$var wire 1 L pdata_a [22] $end
$var wire 1 M pdata_a [21] $end
$var wire 1 N pdata_a [20] $end
$var wire 1 O pdata_a [19] $end
$var wire 1 P pdata_a [18] $end
$var wire 1 Q pdata_a [17] $end
$var wire 1 R pdata_a [16] $end
$var wire 1 S pdata_a [15] $end
$var wire 1 T pdata_a [14] $end
$var wire 1 U pdata_a [13] $end
$var wire 1 V pdata_a [12] $end
$var wire 1 W pdata_a [11] $end
$var wire 1 X pdata_a [10] $end
$var wire 1 Y pdata_a [9] $end
$var wire 1 Z pdata_a [8] $end
$var wire 1 [ pdata_a [7] $end
$var wire 1 \ pdata_a [6] $end
$var wire 1 ] pdata_a [5] $end
$var wire 1 ^ pdata_a [4] $end
$var wire 1 _ pdata_a [3] $end
$var wire 1 ` pdata_a [2] $end
$var wire 1 a pdata_a [1] $end
$var wire 1 b pdata_a [0] $end
$var reg 11 c state_r [10:0] $end
$var reg 11 d next_r [10:0] $end
$var reg 8 e sync1_paddr_r [7:0] $end
$var reg 32 f sync1_pdata_r [31:0] $end
$var reg 8 g sync1_misc_r [7:0] $end
$var reg 8 h in_paddr_r [7:0] $end
$var reg 32 i in_pdata_r [31:0] $end
$var reg 8 j in_misc_r [7:0] $end
$var reg 16 k sl0_tmp_r [15:0] $end
$var reg 16 l sl1_tmp_r [15:0] $end
$var reg 33 m shift_data_r [32:0] $end
$var reg 6 n cycle_cnt_r [5:0] $end
$var reg 6 o bit_cnt_r [5:0] $end
$var reg 32 p buffered_data_r [31:0] $end
$var reg 32 q data_to_send_r [31:0] $end
$var reg 16 r config_r [15:0] $end
$var reg 16 s status_r [15:0] $end
$var reg 1 t parity_ones $end
$var reg 1 u parity_zeroes $end
$var reg 32 v sync1_buffered_data_r [31:0] $end
$var reg 16 w sync1_config_r [15:0] $end
$var reg 16 x sync1_status_r [15:0] $end
$var reg 32 y apb_buffered_data_r [31:0] $end
$var reg 16 z apb_config_r [15:0] $end
$var reg 16 { apb_status_r [15:0] $end
$var reg 32 | apb_muxed_out_r [31:0] $end
$var reg 32 } apb2sl_sync1_data_to_send_r [31:0] $end
$var reg 16 ~ apb2sl_sync1_config_r [15:0] $end
$var reg 32 !! apb2sl_sync2_data_to_send_r [31:0] $end
$var reg 16 "! apb2sl_sync2_config_r [15:0] $end
$var reg 3 #! apb_state [2:0] $end
$var wire 1 $! bit_ended $end
$var wire 1 %! bit_started $end
$upscope $end
$upscope $end
$enddefinitions $end
#0
$dumpvars
b1 c
b1 d
bx e
bx f
bx g
bx h
bx i
bx j
b1010101010101010 k
b1010101010101010 l
b0 m
b0 n
b0 o
b0 p
b0 q
b100000 r
b0 s
1t
0u
b0 v
b0 w
b0 x
b0 y
b0 z
b0 {
bx |
b0 }
b0 ~
b0 !!
b0 "!
bx #!
b1000 !
b1 "
b10 #
b100 $
b1000 %
b0 &
b1 '
b10 (
b11 )
b100 *
b101 +
b110 ,
b111 -
b1000 .
b1001 /
b1010 0
b0 1
zb
za
z`
z_
z^
z]
z\
z[
zZ
zY
zX
zW
zV
zU
zT
zS
zR
zQ
zP
zO
zN
zM
zL
zK
zJ
zI
zH
zG
zF
zE
zD
zC
0$!
0%!
02
03
14
15
06
07
0?
0>
0=
0<
0;
0:
09
08
0@
0A
0B
$end
#50
16
13
b0 c
b1 c
b0 d
b1 d
#100
06
03
#150
16
13
b0 c
b1 c
b0 d
b1 d
#200
06
03
#250
16
13
b0 c
b1 c
b0 d
b1 d
#300
06
03
#350
16
13
b0 c
b1 c
b0 d
b1 d
#400
06
03
#450
16
13
b0 c
b1 c
b0 d
b1 d
#500
06
03
#550
16
13
b0 c
b1 c
b0 d
b1 d
#600
06
03
#650
16
13
b0 c
b1 c
b0 d
b1 d
#700
06
03
#750
16
13
b0 c
b1 c
b0 d
b1 d
#800
06
03
#850
16
13
b0 c
b1 c
b0 d
b1 d
#900
06
03
#950
16
13
b0 c
b1 c
b0 d
b1 d
#1000
17
12
06
03
#1050
16
13
b101010101010101 k
b101010101010101 l
b100000 w
#1100
06
03
#1150
16
13
b1010101010101011 k
b1010101010101011 l
b100000 z
#1200
06
03
#1250
16
13
b101010101010111 k
b101010101010111 l
#1300
06
03
#1350
16
13
b1010101010101111 k
b1010101010101111 l
#1400
06
03
#1450
16
13
b101010101011111 k
b101010101011111 l
#1500
06
03
#1550
16
13
b1010101010111111 k
b1010101010111111 l
#1600
06
03
#1650
16
13
b101010101111111 k
b101010101111111 l
#1700
06
03
#1750
16
13
b1010101011111111 k
b1010101011111111 l
1$!
b0 d
b1 d
#1800
06
03
#1850
16
13
b101010111111111 k
b101010111111111 l
#1900
06
03
#1950
16
13
b1010101111111111 k
b1010101111111111 l
#2000
06
03
#2050
16
13
b101011111111111 k
b101011111111111 l
#2100
06
03
#2150
16
13
b1010111111111111 k
b1010111111111111 l
#2200
06
03
#2250
16
13
b101111111111111 k
b101111111111111 l
#2300
06
03
#2350
16
13
b1011111111111111 k
b1011111111111111 l
#2400
06
03
#2450
16
13
b111111111111111 k
b111111111111111 l
#2500
06
03
#2550
16
13
b1111111111111111 k
b1111111111111111 l
#2600
06
03
#2650
16
13
#2700
06
03
#2750
16
13
#2800
05
b0 d
b1 d
06
03
#2850
16
13
b1111111111111110 l
0$!
b0 d
b1 d
#2900
06
03
#2950
16
13
b1111111111111100 l
#3000
06
03
#3050
16
13
b1111111111111000 l
#3100
06
03
#3150
16
13
b1111111111110000 l
1%!
b0 d
b10 d
#3200
06
03
#3250
16
13
b10 c
b1111111111100000 l
b0 d
b100 d
#3300
06
03
#3350
16
13
b100 c
b1111111111000000 l
b1 n
b10 s
b0 d
b100 d
#3400
06
03
#3450
16
13
b1111111110000000 l
b10 n
b10 x
b0 d
b100 d
#3500
06
03
#3550
16
13
b1111111100000000 l
b11 n
b10 {
b0 d
b100 d
#3600
06
03
#3650
16
13
b1111111000000000 l
b100 n
b0 d
b100 d
#3700
06
03
#3750
16
13
b1111110000000000 l
b101 n
b0 d
b100 d
#3800
06
03
#3850
16
13
b1111100000000000 l
b110 n
b0 d
b100 d
#3900
06
03
#3950
16
13
b1111000000000000 l
b111 n
b0 d
b100 d
#4000
06
03
#4050
16
13
b1110000000000000 l
b1000 n
0%!
b0 d
b10000 d
#4100
06
03
#4150
16
13
b10000 c
b1100000000000000 l
b10000000000000000 m
0t
b1 o
b0 d
b1 d
#4200
06
03
#4250
16
13
b1 c
b1000000000000000 l
b0 n
b0 d
b1 d
#4300
06
03
#4350
16
13
b0 l
#4400
15
b0 d
b1 d
06
03
#4450
16
13
b1 l
#4500
06
03
#4550
16
13
b11 l
#4600
06
03
#4650
16
13
b111 l
#4700
06
03
#4750
16
13
b1111 l
#4800
06
03
#4850
16
13
b11111 l
#4900
06
03
#4950
16
13
b111111 l
#5000
06
03
#5050
16
13
b1111111 l
#5100
06
03
#5150
16
13
b11111111 l
1$!
b0 d
b1 d
#5200
06
03
#5250
16
13
b111111111 l
#5300
06
03
#5350
16
13
b1111111111 l
#5400
06
03
#5450
16
13
b11111111111 l
#5500
06
03
#5550
16
13
b111111111111 l
#5600
06
03
#5650
16
13
b1111111111111 l
#5700
06
03
#5750
16
13
b11111111111111 l
#5800
06
03
#5850
16
13
b111111111111111 l
#5900
06
03
#5950
16
13
b1111111111111111 l
#6000
04
b0 d
b1 d
06
03
#6050
16
13
b1111111111111110 k
0$!
b0 d
b1 d
#6100
06
03
#6150
16
13
b1111111111111100 k
#6200
06
03
#6250
16
13
b1111111111111000 k
#6300
06
03
#6350
16
13
b1111111111110000 k
1%!
b0 d
b100 d
#6400
06
03
#6450
16
13
b100 c
b1111111111100000 k
b1 n
b0 d
b100 d
#6500
06
03
#6550
16
13
b1111111111000000 k
b10 n
b0 d
b100 d
#6600
06
03
#6650
16
13
b1111111110000000 k
b11 n
b0 d
b100 d
#6700
06
03
#6750
16
13
b1111111100000000 k
b100 n
b0 d
b100 d
#6800
06
03
#6850
16
13
b1111111000000000 k
b101 n
b0 d
b100 d
#6900
06
03
#6950
16
13
b1111110000000000 k
b110 n
b0 d
b100 d
#7000
06
03
#7050
16
13
b1111100000000000 k
b111 n
b0 d
b100 d
#7100
06
03
#7150
16
13
b1111000000000000 k
b1000 n
b0 d
b100000 d
#7200
06
03
#7250
16
13
b100000 c
b1110000000000000 k
b1000000000000000 m
1u
b10 o
0%!
b0 d
b1 d
#7300
06
03
#7350
16
13
b1 c
b1100000000000000 k
b0 n
b0 d
b1 d
#7400
06
03
#7450
16
13
b1000000000000000 k
#7500
06
03
#7550
16
13
b0 k
#7600
14
b0 d
b1 d
06
03
#7650
16
13
b1 k
#7700
06
03
#7750
16
13
b11 k
#7800
06
03
#7850
16
13
b111 k
#7900
06
03
#7950
16
13
b1111 k
#8000
06
03
#8050
16
13
b11111 k
#8100
06
03
#8150
16
13
b111111 k
#8200
06
03
#8250
16
13
b1111111 k
#8300
06
03
#8350
16
13
b11111111 k
1$!
b0 d
b1 d
#8400
06
03
#8450
16
13
b111111111 k
#8500
06
03
#8550
16
13
b1111111111 k
#8600
06
03
#8650
16
13
b11111111111 k
#8700
06
03
#8750
16
13
b111111111111 k
#8800
04
b0 d
b1 d
06
03
#8850
16
13
b1111111111110 k
0$!
b0 d
b1 d
#8900
06
03
#8950
16
13
b11111111111100 k
#9000
06
03
#9050
16
13
b111111111111000 k
#9100
06
03
#9150
16
13
b1111111111110000 k
1%!
b0 d
b100 d
#9200
06
03
#9250
16
13
b100 c
b1111111111100000 k
b1 n
b0 d
b100 d
#9300
06
03
#9350
16
13
b1111111111000000 k
b10 n
b0 d
b100 d
#9400
06
03
#9450
16
13
b1111111110000000 k
b11 n
b0 d
b100 d
#9500
06
03
#9550
16
13
b1111111100000000 k
b100 n
b0 d
b100 d
#9600
06
03
#9650
16
13
b1111111000000000 k
b101 n
b0 d
b100 d
#9700
06
03
#9750
16
13
b1111110000000000 k
b110 n
b0 d
b100 d
#9800
06
03
#9850
16
13
b1111100000000000 k
b111 n
b0 d
b100 d
#9900
06
03
#9950
16
13
b1111000000000000 k
b1000 n
b0 d
b100000 d
#10000
06
03
#10050
16
13
b100000 c
b1110000000000000 k
b100000000000000 m
0u
b11 o
0%!
b0 d
b1 d
#10100
06
03
#10150
16
13
b1 c
b1100000000000000 k
b0 n
b0 d
b1 d
#10200
06
03
#10250
16
13
b1000000000000000 k
#10300
06
03
#10350
16
13
b0 k
#10400
14
b0 d
b1 d
06
03
#10450
16
13
b1 k
#10500
06
03
#10550
16
13
b11 k
#10600
06
03
#10650
16
13
b111 k
#10700
06
03
#10750
16
13
b1111 k
#10800
06
03
#10850
16
13
b11111 k
#10900
06
03
#10950
16
13
b111111 k
#11000
06
03
#11050
16
13
b1111111 k
#11100
06
03
